Workbook

Sheet Summary
A1: PlayClaw export | Ticket blast template library
A2: Source: playclaw_export (09-22-2026), n8n "Outreach Reply Logger | VHEA" pinned HubSpot marketing-email data. Counts below are live COUNTIF formulas over the Library tab.
A4: Category | B4: Templates | C4: Teammate-sender templates
A5: Game Ticketblast | B5: =COUNTIF(Library!$A$2:$A$2353,A5) -> 1091 | C5: =COUNTIFS(Library!$A$2:$A$2353,A5,Library!$J$2:$J$2353,"Yes") -> 11
A6: Freemium Tickets (team/state evergreen) | B6: =COUNTIF(Library!$A$2:$A$2353,A6) -> 497 | C6: =COUNTIFS(Library!$A$2:$A$2353,A6,Library!$J$2:$J$2353,"Yes") -> 0
A7: Follow-up | B7: =COUNTIF(Library!$A$2:$A$2353,A7) -> 253 | C7: =COUNTIFS(Library!$A$2:$A$2353,A7,Library!$J$2:$J$2353,"Yes") -> 2
A8: Template (master) | B8: =COUNTIF(Library!$A$2:$A$2353,A8) -> 236 | C8: =COUNTIFS(Library!$A$2:$A$2353,A8,Library!$J$2:$J$2353,"Yes") -> 0
A9: Playoff Blast | B9: =COUNTIF(Library!$A$2:$A$2353,A9) -> 83 | C9: =COUNTIFS(Library!$A$2:$A$2353,A9,Library!$J$2:$J$2353,"Yes") -> 0
A10: Suite Blast | B10: =COUNTIF(Library!$A$2:$A$2353,A10) -> 73 | C10: =COUNTIFS(Library!$A$2:$A$2353,A10,Library!$J$2:$J$2353,"Yes") -> 21
A11: Other / uncategorized | B11: =COUNTIF(Library!$A$2:$A$2353,A11) -> 28 | C11: =COUNTIFS(Library!$A$2:$A$2353,A11,Library!$J$2:$J$2353,"Yes") -> 10
A12: Premium (Club/VIP) Blast | B12: =COUNTIF(Library!$A$2:$A$2353,A12) -> 22 | C12: =COUNTIFS(Library!$A$2:$A$2353,A12,Library!$J$2:$J$2353,"Yes") -> 1
A13: Lower 100s Blast | B13: =COUNTIF(Library!$A$2:$A$2353,A13) -> 21 | C13: =COUNTIFS(Library!$A$2:$A$2353,A13,Library!$J$2:$J$2353,"Yes") -> 0
A14: Demo / meeting | B14: =COUNTIF(Library!$A$2:$A$2353,A14) -> 19 | C14: =COUNTIFS(Library!$A$2:$A$2353,A14,Library!$J$2:$J$2353,"Yes") -> 1
A15: Other Blast | B15: =COUNTIF(Library!$A$2:$A$2353,A15) -> 13 | C15: =COUNTIFS(Library!$A$2:$A$2353,A15,Library!$J$2:$J$2353,"Yes") -> 3
A16: Event / tryout / survey (NYC Basketball legacy) | B16: =COUNTIF(Library!$A$2:$A$2353,A16) -> 8 | C16: =COUNTIFS(Library!$A$2:$A$2353,A16,Library!$J$2:$J$2353,"Yes") -> 8
... A19: Support / transactional | B19: =COUNTIF(Library!$A$2:$A$2353,A19) -> 2 | C19: =COUNTIFS(Library!$A$2:$A$2353,A19,Library!$J$2:$J$2353,"Yes") -> 2
A20: Total | B20: =SUM(B5:B19) -> 2352 | C20: =SUM(C5:C19) -> 59

Sheet Library
A1: Category | B1: Template name | C1: Subject | D1: Sender | E1: Reply-to | F1: Publish date | G1: HubSpot campaign | H1: Source | I1: HubSpot asset ID | J1: Teammate sender (non-Josh) | K1: Mentions Teammate AI | L1: Landing pages | M1: Body (plain text)
A2: Lower 100s Blast | B2: 3/5 Blackhawks @ Mammoth Lower 100s Blast | C2: Invitation to Utah Mammoth Lower 100s Seats | D2: Josh Marcus | E2: josh.marcus@callplaybook.com | F2: 2026-03-05 | G2: Cole Tickets | H2: HubSpot marketing email (Cole Tickets campaign) | I2: 208780891792 | J2: No | K2: No | L2: https://www.callplaybook.com/ | M2: Good morning, My name is Josh Marcus, CEO/Co-Founder of Playbook [https://www.callplaybook.com/]. We wanted to personally invite you to lower 100s seats for the Blackhawks @ Mammoth game on March 12th, including premium seating as thank you for taking a demo of our software Playbook provides tools designed to automate the day-to-day processes of sports organizations, and help business owners save time normally spent completing administrative tasks. If that makes sense for you we would be delighted to connect and have you out for a great game! Are you free to connect tomorrow or sometime next week? Best, Josh Marcus CEO - Playbook Sports
A3: Suite Blast | B3: 3/5 Mavs @ Grizzlies Shared Suite Invitation | C3: Invitation to Memphis Grizzlies Suite | D3: Josh Marcus | E3: josh.marcus@callplaybook.com | F3: 2026-03-05 | G3: Cole Tickets | H3: HubSpot marketing email (Cole Tickets campaign) | I3: 208780874625 | J3: No | K3: No | L3: https://www.callplaybook.com/ | M3: Good morning, My name is Josh Marcus, CEO/Co-Founder of Playbook [https://www.callplaybook.com/]. We wanted to personally invite you to a luxury suite, including food and beverage, for the Grizzlies @ Grizzlies game on March 12th that we are hosting for out top potential youth sports organizations and facilities clients in part of a thank you for taking a demo of the software Playbook provides tools designed to automate the day-to-day processes of sports organizations, and help business owners save time normally spent completing administrative tasks. If that makes sense for you we would be delighted to connect and have you out for a great game! Are you free to connect tomorrow or sometime next week? Best, Josh Marcus CEO - Playbook Sports
A4: Game Ticketblast | B4: 3/5 Iowa @ Nebraska Ticketblast | C4: Quick Call for Iowa vs. Nebraska Tickets? | D4: Josh Marcus | E4: josh.marcus@callplaybook.com | F4: 2026-03-05 | G4: Cole Tickets | H4: HubSpot marketing email (Cole Tickets campaign) | I4: 208780873489 | J4: No | K4: No | L4: https://www.callplaybook.com/ | M4: Good morning, My name is Josh Marcus, CEO/Co-Founder of Playbook [https://www.callplaybook.com/]. We provide tools designed to automate the day-to-day processes of sports organizations, and help business owners save time normally spent completing administrative tasks. We also have a couple extra tickets for the Knicks @ Nuggets game on March 6th and I'd be happy to send a couple over as a gesture of appreciation for your time if you're interested in taking a demo of our platform. Are you free to connect later today or sometime this week? Best, Josh Marcus CEO - Playbook Sports
A5: Game Ticketblast | B5: 3/5 Lakers @ Rockets Ticketblast | C5: Quick Call for Lakers vs. Rockets Tickets? | D5: Josh Marcus | E5: josh.marcus@callplaybook.com | F5: 2026-03-05 | G5: Cole Tickets | H5: HubSpot marketing email (Cole Tickets campaign) | I5: 208780874513 | J5: No | K5: No | L5: https://www.callplaybook.com/ | M5: Good morning, My name is Josh Marcus, CEO/Co-Founder of Playbook [https://www.callplaybook.com/]. We provide tools designed to automate the day-to-day processes of sports organizations, and help business owners save time normally spent completing administrative tasks. We also have a couple extra tickets for the Lakers @ Rockets game on March 16th and I'd be happy to send a couple over as a gesture of appreciation for your time if you're interested in taking a demo of our platform. Are you free to connect tomorrow or sometime next week? Best, Josh Marcus CEO - Playbook Sports
A6: Game Ticketblast | B6: 3/5 Maple Leafs @ Canadiens Ticketblast | C6: Quick Call for Maple Leafs vs. Canadiens Tickets? | D6: Josh Marcus | E6: josh.marcus@callplaybook.com | F6: 2026-03-05 | G6: Cole Tickets | H6: HubSpot marketing email (Cole Tickets campaign) | I6: 208773202224 | J6: No | K6: No | L6: https://www.callplaybook.com/ | M6: Good morning, My name is Josh Marcus, CEO/Co-Founder of Playbook [https://www.callplaybook.com/]. We provide tools designed to automate the day-to-day processes of sports organizations, and help business owners save time normally spent completing administrative tasks. We also have a couple extra tickets for the Maple Leafs @ Canadiens game on March 10th and I'd be happy to send a couple over as a gesture of appreciation for your time if you're interested in taking a demo of our platform. Are you free to connect tomorrow or sometime next week? Best, Josh Marcus CEO - Playbook Sports
A7: Glass Seats Blast | B7: 3/5 Predators @ Canucks Glass Seats Ticketblast | C7: Quick Call for Vancouver Canucks Glass Seats? | D7: Josh Marcus | E7: josh.marcus@callplaybook.com | F7: 2026-03-05 | G7: Cole Tickets | H7: HubSpot marketing email (Cole Tickets campaign) | I7: 208780891716 | J7: No | K7: No | L7: https://www.callplaybook.com/ | M7: Good morning, My name is Josh Marcus, CEO/Co-Founder of Playbook [https://www.callplaybook.com/]. We provide tools designed to automate the day-to-day processes of sports organizations, and help business owners save time normally spent completing administrative tasks. We also have a couple Glass Seats for the Predators @ Canucks game on March 12th and I'd be happy to send a couple over as a gesture of appreciation for your time if you're interested in taking a demo of our platform. Are you free to connect tomorrow or sometime next week? Best, Josh Marcus CEO - Playbook Sports
A8: Suite Blast | B8: 3/5 Zaidman Capitals (Clone) | C8: VIP Suite Invite at Capitals Game | D8: Jake Zaidman | E8: jzaidman@callplaybook.com | F8: 2026-03-05 | G8: Cole Tickets | H8: HubSpot marketing email (Cole Tickets campaign) | I8: 208788212371 | J8: Yes | K8: No | M8: Good afternoon, My name is Jake Zaidman and I am on the partnerships team at Playbook Sports. I wanted to send over an email to extend an invitation to a VIP suite event my company is hosting on March 31st, during a Washington Capitals game for Sports Academy & Facility owners. Drinks are on us! We would love to have you out if you're around! If you're interested, let me know when I can give you a call, or just ring me directly at my cell: 551-236-2814. Best, Jake Playbook Sports
A9: Suite Blast | B9: 3/5 Grizzlies @ 76ers Shared Suite Invitation | C9: Invitation to 76ers Suite | D9: Josh Marcus | E9: josh.marcus@callplaybook.com | F9: 2026-03-05 | G9: Cole Tickets | H9: HubSpot marketing email (Cole Tickets campaign) | I9: 208774695982 | J9: No | K9: No | L9: https://www.callplaybook.com/ | M9: Good morning, My name is Josh Marcus, CEO/Co-Founder of Playbook [https://www.callplaybook.com/]. We wanted to personally invite you to a luxury suite, including food and beverage, for the Grizzlies @ 76ers game on March 10th that we are hosting for out top potential youth sports organizations and facilities clients in part of a thank you for taking a demo of the software Playbook provides tools designed to automate the day-to-day processes of sports organizations, and help business owners save time normally spent completing administrative tasks. If that makes sense for you we would be delighted to connect and have you out for a great game! Are you free to connect tomorrow or sometime next week? Best, Josh Marcus CEO - Playbook Sports
A10: Suite Blast | B10: 3/5 Wizards @ Pelicans Shared Suite Invitation | C10: Invitation to Pelicans Suite | D10: Josh Marcus | E10: josh.marcus@callplaybook.com | F10: 2026-03-05 | G10: Cole Tickets | H10: HubSpot marketing email (Cole Tickets campaign) | I10: 208770538255 | J10: No | K10: No | L10: https://www.callplaybook.com/ | M10: Good morning, My name is Josh Marcus, CEO/Co-Founder of Playbook [https://www.callplaybook.com/]. We wanted to personally invite you to a luxury suite for the Wizards @ Pelicans game on March 8th that we are hosting for out top potential youth sports organizations and facilities clients in part of a thank you for taking a demo of the software Playbook provides tools designed to automate the day-to-day processes of sports organizations, and help business owners save time normally spent completing administrative tasks. If that makes sense for you we would be delighted to connect and have you out for a great game! Are you free to connect tomorrow or sometime next week? Best, Josh Marcus CEO - Playbook Sports
A11: Glass Seats Blast | B11: 3/5 Islanders @ Senators Glass Seats Ticketblast | C11: Quick Call for Ottawa Senators Glass Seats? | D11: Josh Marcus | E11: josh.marcus@callplaybook.com | F11: 2026-03-05 | G11: Cole Tickets | H11: HubSpot marketing email (Cole Tickets campaign) | I11: 208770537237 | J11: No | K11: No | L11: https://www.callplaybook.com/ | M11: Good morning, My name is Josh Marcus, CEO/Co-Founder of Playbook [https://www.callplaybook.com/]. We provide tools designed to automate the day-to-day processes of sports organizations, and help business owners save time normally spent completing administrative tasks. We also have a couple Glass Seats for the Islanders @ Senators game on March 19th and I'd be happy to send a couple over as a gesture of appreciation for your time if you're interested in taking a demo of our platform. Are you free to connect tomorrow or sometime next week? Best, Josh Marcus CEO - Playbook Sports
A12: Suite Blast | B12: 3/5 Zaidman Capitals (Clone) | C12: VIP Suite Invite at Capitals Game | D12: Jake Zaidman | E12: jzaidman@callplaybook.com | F12: 2026-03-05 | G12: Cole Tickets | H12: HubSpot marketing email (live API page) | I12: 208788212371 | J12: Yes | K12: No | M12: Good afternoon, My name is Jake Zaidman and I am on the partnerships team at Playbook Sports. I wanted to send over an email to extend an invitation to a VIP suite event my company is hosting on March 31st, during a Washington Capitals game for Sports Academy & Facility owners. Drinks are on us! We would love to have you out if you're around! If you're interested, let me know when I can give you a call, or just ring me directly at my cell: 551-236-2814. Best, Jake Playbook Sports
A13: Game Ticketblast | B13: 3/5 Lakers @ Rockets Ticketblast | C13: Quick Call for Lakers vs. Rockets Tickets? | D13: Josh Marcus | E13: josh.marcus@callplaybook.com | F13: 2026-03-05 | G13: Cole Tickets | H13: HubSpot marketing email (live API page) | I13: 208780874513 | J13: No | K13: No | L13: https://www.callplaybook.com/ | M13: Good morning, My name is Josh Marcus, CEO/Co-Founder of Playbook [https://www.callplaybook.com/]. We provide tools designed to automate the day-to-day processes of sports organizations, and help business owners save time normally spent completing administrative tasks. We also have a couple extra tickets for the Lakers @ Rockets game on March 16th and I'd be happy to send a couple over as a gesture of appreciation for your time if you're interested in taking a demo of our platform. Are you free to connect tomorrow or sometime next week? Best, Josh Marcus CEO - Playbook Sports
A14: Lower 100s Blast | B14: 3/5 Blackhawks @ Mammoth Lower 100s Blast | C14: Invitation to Utah Mammoth Lower 100s Seats | D14: Josh Marcus | E14: josh.marcus@callplaybook.com | F14: 2026-03-05 | G14: Cole Tickets | H14: HubSpot marketing email (live API page) | I14: 208780891792 | J14: No | K14: No | L14: https://www.callplaybook.com/ | M14: Good morning, My name is Josh Marcus, CEO/Co-Founder of Playbook [https://www.callplaybook.com/]. We wanted to personally invite you to lower 100s seats for the Blackhawks @ Mammoth game on March 12th, including premium seating as thank you for taking a demo of our software Playbook provides tools designed to automate the day-to-day processes of sports organizations, and help business owners save time normally spent completing administrative tasks. If that makes sense for you we would be delighted to connect and have you out for a great game! Are you free to connect tomorrow or sometime next week? Best, Josh Marcus CEO - Playbook Sports
A15: Glass Seats Blast | B15: 3/5 Predators @ Canucks Glass Seats Ticketblast | C15: Quick Call for Vancouver Canucks Glass Seats? | D15: Josh Marcus | E15: josh.marcus@callplaybook.com | F15: 2026-03-05 | G15: Cole Tickets | H15: HubSpot marketing email (live API page) | I15: 208780891716 | J15: No | K15: No | L15: https://www.callplaybook.com/ | M15: Good morning, My name is Josh Marcus, CEO/Co-Founder of Playbook [https://www.callplaybook.com/]. We provide tools designed to automate the day-to-day processes of sports organizations, and help business owners save time normally spent completing administrative tasks. We also have a couple Glass Seats for the Predators @ Canucks game on March 12th and I'd be happy to send a couple over as a gesture of appreciation for your time if you're interested in taking a demo of our platform. Are you free to connect tomorrow or sometime next week? Best, Josh Marcus CEO - Playbook Sports
A16: Suite Blast | B16: 3/5 Mavs @ Grizzlies Shared Suite Invitation | C16: Invitation to Memphis Grizzlies Suite | D16: Josh Marcus | E16: josh.marcus@callplaybook.com | F16: 2026-03-05 | G16: Cole Tickets | H16: HubSpot marketing email (live API page) | I16: 208780874625 | J16: No | K16: No | L16: https://www.callplaybook.com/ | M16: Good morning, My name is Josh Marcus, CEO/Co-Founder of Playbook [https://www.callplaybook.com/]. We wanted to personally invite you to a luxury suite, including food and beverage, for the Grizzlies @ Grizzlies game on March 12th that we are hosting for out top potential youth sports organizations and facilities clients in part of a thank you for taking a demo of the software Playbook provides tools designed to automate the day-to-day processes of sports organizations, and help business owners save time normally spent completing administrative tasks. If that makes sense for you we would be delighted to connect and have you out for a great game! Are you free to connect tomorrow or sometime next week? Best, Josh Marcus CEO - Playbook Sports
A17: Game Ticketblast | B17: 3/5 Iowa @ Nebraska Ticketblast | C17: Quick Call for Iowa vs. Nebraska Tickets? | D17: Josh Marcus | E17: josh.marcus@callplaybook.com | F17: 2026-03-05 | G17: Cole Tickets | H17: HubSpot marketing email (live API page) | I17: 208780873489 | J17: No | K17: No | L17: https://www.callplaybook.com/ | M17: Good morning, My name is Josh Marcus, CEO/Co-Founder of Playbook [https://www.callplaybook.com/]. We provide tools designed to automate the day-to-day processes of sports organizations, and help business owners save time normally spent completing administrative tasks. We also have a couple extra tickets for the Knicks @ Nuggets game on March 6th and I'd be happy to send a couple over as a gesture of appreciation for your time if you're interested in taking a demo of our platform. Are you free to connect later today or sometime this week? Best, Josh Marcus CEO - Playbook Sports
A18: Suite Blast | B18: 3/5 Wizards @ Pelicans Shared Suite Invitation | C18: Invitation to Pelicans Suite | D18: Josh Marcus | E18: josh.marcus@callplaybook.com | F18: 2026-03-05 | G18: Cole Tickets | H18: HubSpot marketing email (live API page) | I18: 208770538255 | J18: No | K18: No | L18: https://www.callplaybook.com/ | M18: Good morning, My name is Josh Marcus, CEO/Co-Founder of Playbook [https://www.callplaybook.com/]. We wanted to personally invite you to a luxury suite for the Wizards @ Pelicans game on March 8th that we are hosting for out top potential youth sports organizations and facilities clients in part of a thank you for taking a demo of the software Playbook provides tools designed to automate the day-to-day processes of sports organizations, and help business owners save time normally spent completing administrative tasks. If that makes sense for you we would be delighted to connect and have you out for a great game! Are you free to connect tomorrow or sometime next week? Best, Josh Marcus CEO - Playbook Sports
A19: Suite Blast | B19: 3/5 Grizzlies @ 76ers Shared Suite Invitation | C19: Invitation to 76ers Suite | D19: Josh Marcus | E19: josh.marcus@callplaybook.com | F19: 2026-03-05 | G19: Cole Tickets | H19: HubSpot marketing email (live API page) | I19: 208774695982 | J19: No | K19: No | L19: https://www.callplaybook.com/ | M19: Good morning, My name is Josh Marcus, CEO/Co-Founder of Playbook [https://www.callplaybook.com/]. We wanted to personally invite you to a luxury suite, including food and beverage, for the Grizzlies @ 76ers game on March 10th that we are hosting for out top potential youth sports organizations and facilities clients in part of a thank you for taking a demo of the software Playbook provides tools designed to automate the day-to-day processes of sports organizations, and help business owners save time normally spent completing administrative tasks. If that makes sense for you we would be delighted to connect and have you out for a great game! Are you free to connect tomorrow or sometime next week? Best, Josh Marcus CEO - Playbook Sports
A20: Game Ticketblast | B20: 3/5 Maple Leafs @ Canadiens Ticketblast | C20: Quick Call for Maple Leafs vs. Canadiens Tickets? | D20: Josh Marcus | E20: josh.marcus@callplaybook.com | F20: 2026-03-05 | G20: Cole Tickets | H20: HubSpot marketing email (live API page) | I20: 208773202224 | J20: No | K20: No | L20: https://www.callplaybook.com/ | M20: Good morning, My name is Josh Marcus, CEO/Co-Founder of Playbook [https://www.callplaybook.com/]. We provide tools designed to automate the day-to-day processes of sports organizations, and help business owners save time normally spent completing administrative tasks. We also have a couple extra tickets for the Maple Leafs @ Canadiens game on March 10th and I'd be happy to send a couple over as a gesture of appreciation for your time if you're interested in taking a demo of our platform. Are you free to connect tomorrow or sometime next week? Best, Josh Marcus CEO - Playbook Sports
A21: Glass Seats Blast | B21: 3/5 Islanders @ Senators Glass Seats Ticketblast | C21: Quick Call for Ottawa Senators Glass Seats? | D21: Josh Marcus | E21: josh.marcus@callplaybook.com | F21: 2026-03-05 | G21: Cole Tickets | H21: HubSpot marketing email (live API page) | I21: 208770537237 | J21: No | K21: No | L21: https://www.callplaybook.com/ | M21: Good morning, My name is Josh Marcus, CEO/Co-Founder of Playbook [https://www.callplaybook.com/]. We provide tools designed to automate the day-to-day processes of sports organizations, and help business owners save time normally spent completing administrative tasks. We also have a couple Glass Seats for the Islanders @ Senators game on March 19th and I'd be happy to send a couple over as a gesture of appreciation for your time if you're interested in taking a demo of our platform. Are you free to connect tomorrow or sometime next week? Best, Josh Marcus CEO - Playbook Sports
A22: Suite Blast | B22: 3/30 Rays @ Brewers Ticketblast | C22: VIP Suite Invite HOME OPENER - Rays @ Brewers | D22: Danny Coleman | E22: danny@callplaybook.com | F22: 2026-03-04 | G22: Cole Tickets | H22: HubSpot marketing email (Cole Tickets campaign) | I22: 208716383305 | J22: Yes | K22: No | M22: Hello, My name is Danny Coleman and I am on the partnerships team at Playbook Sports. I wanted to send over an email to extend an invitation to a VIP suite event my company is hosting on March 30, during a Milwaukee Brewers game for sports organization managers and owners. Tickets are on us! We would love to have you out if you're around. Please let me know if you're interested!. Best, Danny Partnerships - Playbook Sports
A23: Lower 100s Blast | B23: 3/4 76ers @ Hawks Lower 100s Blast | C23: Invitation to Atlanta Hawks Lower 100s Seats | D23: Josh Marcus | E23: josh.marcus@callplaybook.com | F23: 2026-03-04 | G23: Cole Tickets | H23: HubSpot marketing email (Cole Tickets campaign) | I23: 208709657517 | J23: No | K23: No | L23: https://www.callplaybook.com/ | M23: Good morning, My name is Josh Marcus, CEO/Co-Founder of Playbook [https://www.callplaybook.com/]. We wanted to personally invite you to lower 100s seats for the 76ers @ Hawks game on March 7th, including premium seating as thank you for taking a demo of our software Playbook provides tools designed to automate the day-to-day processes of sports organizations, and help business owners save time normally spent completing administrative tasks. If that makes sense for you we would be delighted to connect and have you out for a great game! Are you free to connect sometime today or later this week? Best, Josh Marcus CEO - Playbook Sports
A24: Game Ticketblast | B24: 3/4 Knicks @ Nuggets Ticketblast | C24: Quick Call for Knicks vs. Nuggets Tickets? | D24: Josh Marcus | E24: josh.marcus@callplaybook.com | F24: 2026-03-04 | G24: Cole Tickets | H24: HubSpot marketing email (Cole Tickets campaign) | I24: 208720925069 | J24: No | K24: No | L24: https://www.callplaybook.com/ | M24: Good morning, My name is Josh Marcus, CEO/Co-Founder of Playbook [https://www.callplaybook.com/]. We provide tools designed to automate the day-to-day processes of sports organizations, and help business owners save time normally spent completing administrative tasks. We also have a couple extra tickets for the Knicks @ Nuggets game on March 6th and I'd be happy to send a couple over as a gesture of appreciation for your time if you're interested in taking a demo of our platform. Are you free to connect later today or sometime this week? Best, Josh Marcus CEO - Playbook Sports
A25: Game Ticketblast | B25: 3/4 Oilers @ Golden Knights Ticketblast | C25: Quick Call for Oilers vs. Golden Knights Tickets? | D25: Josh Marcus | E25: josh.marcus@callplaybook.com | F25: 2026-03-04 | G25: Cole Tickets | H25: HubSpot marketing email (Cole Tickets campaign) | I25: 208720677406 | J25: No | K25: No | L25: https://www.callplaybook.com/ | M25: Good morning, My name is Josh Marcus, CEO/Co-Founder of Playbook [https://www.callplaybook.com/]. We provide tools designed to automate the day-to-day processes of sports organizations, and help business owners save time normally spent completing administrative tasks. We also have a couple extra tickets for the Oilers @ Golden Knights game on March 8th and I'd be happy to send a couple over as a gesture of appreciation for your time if you're interested in taking a demo of our platform. Are you free to connect later today or sometime this week? Best, Josh Marcus CEO - Playbook Sports
A26: Lower 100s Blast | B26: 3/4 Magic @ Timberwolves Lower 100s Blast | C26: Invitation to Minnesota Timberwolves Lower 100s Seats | D26: Josh Marcus | E26: josh.marcus@callplaybook.com | F26: 2026-03-04 | G26: Cole Tickets | H26: HubSpot marketing email (Cole Tickets campaign) | I26: 208709657693 | J26: No | K26: No | L26: https://www.callplaybook.com/ | M26: Good morning, My name is Josh Marcus, CEO/Co-Founder of Playbook [https://www.callplaybook.com/]. We wanted to personally invite you to lower 100s seats for the Magic @ Timberwolves game on March 7th, including premium seating as thank you for taking a demo of our software Playbook provides tools designed to automate the day-to-day processes of sports organizations, and help business owners save time normally spent completing administrative tasks. If that makes sense for you we would be delighted to connect and have you out for a great game! Are you free to connect sometime today or later this week? Best, Josh Marcus CEO - Playbook Sports
A27: Game Ticketblast | B27: 3/4 Canucks @ Blackhawks Ticketblast | C27: Quick Call for Chicago Blackhawks Tickets? | D27: Josh Marcus | E27: josh.marcus@callplaybook.com | F27: 2026-03-04 | G27: Cole Tickets | H27: HubSpot marketing email (Cole Tickets campaign) | I27: 208709657762 | J27: No | K27: No | L27: https://www.callplaybook.com/ | M27: Good morning, My name is Josh Marcus, CEO/Co-Founder of Playbook [https://www.callplaybook.com/]. We provide tools designed to automate the day-to-day processes of sports organizations, and help business owners save time normally spent completing administrative tasks. We also have a couple extra tickets for the Canucks @ Blackhawks game on March 6th and I'd be happy to send a couple over as a gesture of appreciation for your time if you're interested in taking a demo of our platform. Are you free to connect later today or sometime this week? Best, Josh Marcus CEO - Playbook Sports
A28: Game Ticketblast | B28: 3/4 Warriors @ Thunder Ticketblast | C28: Quick Call for Warriors vs. Thunder Tickets? | D28: Josh Marcus | E28: josh.marcus@callplaybook.com | F28: 2026-03-04 | G28: Cole Tickets | H28: HubSpot marketing email (Cole Tickets campaign) | I28: 208720618398 | J28: No | K28: No | L28: https://www.callplaybook.com/ | M28: Good morning, My name is Josh Marcus, CEO/Co-Founder of Playbook [https://www.callplaybook.com/]. We provide tools designed to automate the day-to-day processes of sports organizations, and help business owners save time normally spent completing administrative tasks. We also have a couple extra tickets for the Warriors @ Thunder game on March 7th and I'd be happy to send a couple over as a gesture of appreciation for your time if you're interested in taking a demo of our platform. Are you free to connect later today or sometime this week? Best, Josh Marcus CEO - Playbook Sports
A29: Game Ticketblast | B29: 3/4 Knicks @ Nuggets Ticketblast | C29: Quick Call for Knicks vs. Nuggets Tickets? | D29: Josh Marcus | E29: josh.marcus@callplaybook.com | F29: 2026-03-04 | G29: Cole Tickets | H29: HubSpot marketing email (live API page) | I29: 208720925069 | J29: No | K29: No | L29: https://www.callplaybook.com/ | M29: Good morning, My name is Josh Marcus, CEO/Co-Founder of Playbook [https://www.callplaybook.com/]. We provide tools designed to automate the day-to-day processes of sports organizations, and help business owners save time normally spent completing administrative tasks. We also have a couple extra tickets for the Knicks @ Nuggets game on March 6th and I'd be happy to send a couple over as a gesture of appreciation for your time if you're interested in taking a demo of our platform. Are you free to connect later today or sometime this week? Best, Josh Marcus CEO - Playbook Sports
A30: Game Ticketblast | B30: 3/4 Warriors @ Thunder Ticketblast | C30: Quick Call for Warriors vs. Thunder Tickets? | D30: Josh Marcus | E30: josh.marcus@callplaybook.com | F30: 2026-03-04 | G30: Cole Tickets | H30: HubSpot marketing email (live API page) | I30: 208720618398 | J30: No | K30: No | L30: https://www.callplaybook.com/ | M30: Good morning, My name is Josh Marcus, CEO/Co-Founder of Playbook [https://www.callplaybook.com/]. We provide tools designed to automate the day-to-day processes of sports organizations, and help business owners save time normally spent completing administrative tasks. We also have a couple extra tickets for the Warriors @ Thunder game on March 7th and I'd be happy to send a couple over as a gesture of appreciation for your time if you're interested in taking a demo of our platform. Are you free to connect later today or sometime this week? Best, Josh Marcus CEO - Playbook Sports
A31: Game Ticketblast | B31: 3/4 Oilers @ Golden Knights Ticketblast | C31: Quick Call for Oilers vs. Golden Knights Tickets? | D31: Josh Marcus | E31: josh.marcus@callplaybook.com | F31: 2026-03-04 | G31: Cole Tickets | H31: HubSpot marketing email (live API page) | I31: 208720677406 | J31: No | K31: No | L31: https://www.callplaybook.com/ | M31: Good morning, My name is Josh Marcus, CEO/Co-Founder of Playbook [https://www.callplaybook.com/]. We provide tools designed to automate the day-to-day processes of sports organizations, and help business owners save time normally spent completing administrative tasks. We also have a couple extra tickets for the Oilers @ Golden Knights game on March 8th and I'd be happy to send a couple over as a gesture of appreciation for your time if you're interested in taking a demo of our platform. Are you free to connect later today or sometime this week? Best, Josh Marcus CEO - Playbook Sports
A32: Freemium Tickets (team/state evergreen) | B32: Columbus Freemium Tickets Email (BDA Suite Blast) | C32: Columbus Pro Sports Tickets from Playbook Sports | D32: Josh Marcus | E32: jmarcus@callplaybook.com | F32: 2026-03-04 | G32: BDA Suite Blast | H32: HubSpot marketing email (live API page) | I32: 208716075633 | J32: No | K32: No | L32: https://www.callplaybook.com/columbus-ticket-registration | https://www.callplaybook.com/get-started | M32: Hi, My name is Josh Marcus and I am the CEO and Founder of Playbook Sports [https://www.callplaybook.com/get-started], an all-in-one sports management software solution designed for ease of use and simplifying processes. To the start the year off with some energy, we're donating sports tickets to leaders in Columbus. I just reached out via text but wanted to follow up here and say I have Columbus Crew, Columbus Blue Jackets and Ohio State Buckeyes Men's Basketball tickets for games this season, at home, that I would like to donate to you for being an awesome leader in sports. Feel free to pick one of the form links [https://www.callplaybook.com/columbus-ticket-registration] below or just reply to this email with which team you would like to claim tickets for. Playbook will follow up and confirm your reservation. 1. Columbus Crew [https://www.callplaybook.com/columbus-ticket-registration] 2. Columbus Blue Jackets [https://www.callplaybook.com/columbus-ticket-registration] 3. Ohio State Buckeyes Men's Basketball [https://www.callplaybook.com/columbus-ticket-registration] We hope to connect soon and see you at a game! Sincerely, Josh We are offering these tickets in tandem with a free software demo over Zoom where you will learn a bit about how we help organizations like yours beyond just donating awesome sports tickets.
A33: Freemium Tickets (team/state evergreen) | B33: WV Freemium Ticket View 7/8 (BDA Suite Blast) | C33: Would you like to attend a Pro Sports Game??? | D33: Josh Marcus | E33: jmarcus@callplaybook.com | F33: 2026-03-04 | G33: BDA Suite Blast | H33: HubSpot marketing email (live API page) | I33: 208720175894 | J33: No | K33: No | L33: https://www.callplaybook.com/features | M33: Hi, I am Josh Marcus, Founder / CEO of Playbook Sports [https://www.callplaybook.com/features], a SAAS tool designed to automate all day to day processes for sports organizations. I came across the {{ company.name }} website and had to commend you for your contribution to your community. I was hoping I could link with you over a quick Zoom call, learn more about your organization and your future endeavors. I can also show you how Playbook Software has been working with other organizations to help them save admin time, and generate additional signups for your programs! I would love to throw in free MLB tickets to the Nationals, Guardians and the Phillies. Let me know if you have a time that works conveniently for you in the coming weeks and we'd be thrilled to speak with you. Have a good and I look forward to chatting with you further. Thanks, Josh Marcus CEO - Playbook Sports
A34: Game Ticketblast | B34: Enterprise Ticket Marketing Email May 12 (BDA Suite Blast) | C34: Would you like to attend a Pro Sports Game??? | D34: Josh Marcus | E34: jmarcus@callplaybook.com | F34: 2026-03-04 | G34: BDA Suite Blast | H34: HubSpot marketing email (live API page) | I34: 208716094056 | J34: No | K34: No | L34: https://www.callplaybook.com/features | M34: Hi, I am Josh Marcus, Founder / CEO of Playbook Sports [https://www.callplaybook.com/features], a SAAS tool designed to automate all day to day processes for sports organization. I came across the {{ company.name }} website and had to commend you for your contribution to your community. I was hoping I could link with you over a quick zoom call, learn more about your organization and show you our software. We'd love to get your feedback on our product and gain some perspective from you. I am happy to throw in free tickets to an MLB or MLS for you to attend as well. Let me know if you have a time that works conveniently for you in the coming week and I will be thrilled to speak with you. Have a super weekend and I look forward to chatting with you further. Thanks, Josh Marcus Playbook Sports
... A41: Freemium Tickets (team/state evergreen) | B41: Georgia Freemium Ticket View 12/12 (BDA Suite Blast) | C41: Would you like to see a Hawks, Falcons or CBB game on Playbook? | D41: Josh Marcus | E41: jmarcus@callplaybook.com | F41: 2026-03-04 | G41: BDA Suite Blast | H41: HubSpot marketing email (live API page) | I41: 208716075626 | J41: No | K41: No | L41: https://www.callplaybook.com/features | M41: Hi, I'm Josh Marcus, Founder and CEO of Playbook Sports [https://www.callplaybook.com/features]. We're a SAAS tool designed to automate the day to day processes for sports and multi-purpose organizations and help them save time spent doing repetitive administrative tasks. I came across the {{ company.name }} website and it seems like you guys are running a fantastic operation; I believe Playbook would be a great fit for you and your team. I was hoping to link with you over a quick Zoom call to learn more about your organization, and show you exactly how Playbook can be a fit to help save admin time and provide a more streamlined experience for your participants! I would love to throw in two free tickets to the following Hawks, Falcons or College Basketball games as well: - Hawks vs. Chicago Bulls (12/21) - Hawks vs. Detroit Pistons (12/23) - Falcons vs. Arizona Cardinals (01/01) - Alabama Basketball vs. Ole Miss (01/03) - Georgia Basketball vs. Auburn (01/12) Let me know if you'd have some time to chat in the coming weeks and we'd be thrilled to speak with you! Thanks, Josh Marcus CEO - Playbook Sports
A42: Game Ticketblast | B42: Minnesota Ticket Marketing Email May 16 (BDA Suite Blast) | C42: Would you like to attend a Pro Sports Game??? | D42: Josh Marcus | E42: jmarcus@callplaybook.com | F42: 2026-03-04 | H42: HubSpot marketing email (live API page) | I42: 208715415964 | J42: No | K42: No | L42: https://www.callplaybook.com/features | M42: Hi, I am Josh Marcus, Founder / CEO of Playbook Sports [https://www.callplaybook.com/features], a SAAS tool designed to automate all day to day processes for sports organization. I came across the {{ company.name }} website and had to commend you for your contribution to your community. I was hoping I could link with you over a quick zoom call, learn more about your organization and show you our software. We'd love to show you how Playbook Software can help you save admin time, and generate additional signups for your programs! I am happy to throw in free tickets to a Twins, Lynx or Minnesota United FC game for you to attend as well. Let me know if you have a time that works conveniently for you in the coming week and I will be thrilled to speak with you. Have a super weekend and I look forward to chatting with you further. Thanks, Josh Marcus Playbook Sports
A43: Freemium Tickets (team/state evergreen) | B43: Seattle non-specific Freemium Ticket View 8/22 (BDA Suite Blast) | C43: Would you like to attend a Seattle Sounders Game on Playbook? | D43: Josh Marcus | E43: jmarcus@callplaybook.com | F43: 2026-03-04 | G43: BDA Suite Blast | H43: HubSpot marketing email (live API page) | I43: 208720327056 | J43: No | K43: No | L43: https://www.callplaybook.com/features | M43: Hi, I'm Josh Marcus, Founder and CEO of Playbook Sports [https://www.callplaybook.com/features]. We're a SAAS tool designed to automate the day to day processes for sports and multi-purpose organizations and help them save time spent doing repetitive administrative tasks. I came across the {{ company.name }} website and it seems like you guys are running a fantastic operation; I believe Playbook would be a great fit for you and your team. I was hoping to link with you over a quick Zoom call to learn more about your organization, and show you exactly how Playbook can be a fit to help save admin time and provide a more streamlined experience for your participants as well! I would love to throw in free Mariners or Sounders FC tickets to one of the following games as well: - Mariners v. Braves (9/10) - Mariners v. Padres (9/14) - Mariners v. Rangers (9/27) - Sounders v. Houston Dynamo (9/4) - Sounders v. FC Cincinnati (9/27) - Sounders v. San Jose Earthquakes (10/9). Let me know if you'd have some time to chat in the coming weeks and we'd be thrilled to speak with you! Thanks, Josh Marcus CEO - Playbook Sports
A44: Freemium Tickets (team/state evergreen) | B44: Florida All Teams Freemium Tickets Email (BDA Suite Blast) | C44: Your Florida Pro Sports Tickets from Playbook Sports | D44: Josh Marcus | E44: jmarcus@callplaybook.com | F44: 2026-03-04 | G44: BDA Suite Blast | H44: HubSpot marketing email (live API page) | I44: 208719837589 | J44: No | K44: No | L44: https://www.callplaybook.com/florida-ticket-registration | https://www.callplaybook.com/get-started | M44: Hi, My name is Josh Marcus and I am the CEO and Founder of Playbook Sports [https://www.callplaybook.com/get-started], an all-in-one sports management software solution designed for ease of use and simplifying processes for you and your players. I'm looking to connect with awesome community leaders like you in Florida. To break the ice, I'm donating pro sports tickets and want you to take advantage of this offer. I have Heat, Magic, Lightning, and Panthers tickets for games this season at home (I also have tickets to the Rays, Marlins, Orlando City SC, and Inter Miami CF). If you are interested, all I ask is your time for a free software demo with Playbook, more info below. Feel free to pick one of the form links [https://www.callplaybook.com/florida-ticket-registration] below or just reply to this email with which team you would like to claim tickets for, Playbook will follow up and confirm your reservation. 1. Miami Heat [https://www.callplaybook.com/florida-ticket-registration] 2. Orlando Magic [https://www.callplaybook.com/florida-ticket-registration] 3. Tampa Bay Lightning [https://www.callplaybook.com/florida-ticket-registration] 4. Florida Panthers [https://www.callplaybook.com/florida-ticket-registration] 5. Rays/Marlins/Orlando City/Inter Miami Ticket Request [https://www.callplaybook.com/florida-ticket-registration] We hope to connect soon and see you at a game! Sincerely, Josh We are offering these tickets in tandem with a free software demo over Zoom where you will learn a bit about how we help organizations like yours beyond donating awesome sports tickets. In our demo, we will walk you through our relevant features, what it would look and feel like for you and your customers to use it, and show you how we stand out from other software providers. It's an awesome way to see what else is out there in sports tech even if you cannot make a software switch right now.
A45: Game Ticketblast | B45: Ohio Ticket Marketing Email 3/29 (BDA Suite Blast) | C45: Would you like to attend a Pro Sports Game??? | D45: Josh Marcus | E45: jmarcus@callplaybook.com | F45: 2026-03-04 | H45: HubSpot marketing email (live API page) | I45: 208718954898 | J45: No | K45: No | L45: https://www.callplaybook.com/features | M45: Hi, I am Josh Marcus, Founder / CEO of Playbook Sports [https://www.callplaybook.com/features], a SAAS tool designed designed to automate all day to day processes for sports organization. I came across the {{ company.name }} website and had to commend you for your contribution to your community. I was hoping I could link with you over a quick zoom call, learn more about your organization and show your our software. We'd love to get your feedback on our product and gain some perspective from you. I am happy to throw in free tickets to a pro sports game for you to attend as well. Let me know if you have a time that works conveniently for you in the coming week and I will be thrilled to speak with you. Have a super weekend and I look forward to chatting with you further. Thanks, Josh Marcus Playbook Sports
A46: Demo / meeting | B46: FedEx Sideline Space for Demo Email (Mindbody Leads) (BDA Suite Blast) | C46: Free Field Slots at FedEx Field, Playbook Sports Events Special | D46: Josh Marcus | E46: jmarcus@callplaybook.com | F46: 2026-03-04 | G46: BDA Suite Blast | H46: HubSpot marketing email (live API page) | I46: 208720175888 | J46: No | K46: No | L46: http://www.callplaybook.com/features | M46: Hello, I hope you are well. I am reaching out from Playbook Sports [http://www.callplaybook.com/features] because we have some field space available on the FedEx Field sideline and I think your program would be a great fit. I saw your organization while looking through local programs and think you would be able to run an awesome class, clinic, or training session with that hour of free field time. You can take advantage of the space for photos for your organization's social media and invite fans and family to come to watch. Are you interested in booking that field time at FedEx Field and a free software demo with Playbook? Sincerely, Josh I think we would be a great fit for you as a software partner too. Our software is built to streamline registration, member management, scheduling/staffing, financial reporting, and much more so that operating a community activities business is as easy as possible. For all organizations doing a stadium event with us, we provide a free demo of our software in a 20 or so minute, free, online meeting where we can compare what we offer to Mindbody.
A47: Freemium Tickets (team/state evergreen) | B47: Detroit Freemium Other (BDA Suite Blast) | C47: Would you like to attend a Pro Sports Game??? | D47: Josh Marcus | E47: jmarcus@callplaybook.com | F47: 2026-03-04 | G47: BDA Suite Blast | H47: HubSpot marketing email (live API page) | I47: 208718954895 | J47: No | K47: No | L47: https://www.callplaybook.com/features | M47: I'm Josh Marcus, Founder and CEO of Playbook Sports [https://www.callplaybook.com/features]. We're a SAAS tool designed to automate the day to day processes for sports and multi-purpose organizations and help them save time spent doing repetitive administrative tasks. I came across the {{ company.name }} website and it seems like you guys are running a fantastic operation; I believe Playbook would be a great fit for you and your team. I was hoping to link with you over a quick Zoom call to learn more about your organization, and show you exactly how Playbook can be a fit to help save admin time and provide a more streamlined exeprience for your participants as well! I would love to throw in free tickets to the Lions vs Commanders (9/18), Lions vs Jaguars (12/4) or Red Wings vs Canadiens (11/8) as well. Let me know if you'd have some time to chat in the coming weeks and we'd be thrilled to speak with you! Thanks, Josh Marcus CEO - Playbook Sports
A48: Freemium Tickets (team/state evergreen) | B48: Iowa Freemium View 10/07 (Clone) (BDA Suite Blast) | C48: Would you like to attend a CFB/CBB Game on Playbook? | D48: Josh Marcus | E48: jmarcus@callplaybook.com | F48: 2026-03-04 | H48: HubSpot marketing email (live API page) | I48: 208720045848 | J48: No | K48: No | L48: https://www.callplaybook.com/features | M48: Hi, I'm Josh Marcus, Founder and CEO of Playbook Sports [https://www.callplaybook.com/features]. We're a SAAS tool designed to automate the day to day processes for sports and multi-purpose organizations and help them save time spent doing repetitive administrative tasks. I came across the {{ company.name }} website and it seems like you guys are running a fantastic operation; I believe Playbook would be a great fit for you and your team. I was hoping to link with you over a quick Zoom call to learn more about your organization, and show you exactly how Playbook can be a fit to help save admin time and provide a more streamlined experience for your participants! I would love to throw in free tickets to the following Iowa and Iowa State games as well: - Iowa State Cyclones Football vs. West Virginia (11/05) - Iowa State Cyclones Football vs. Texas Tech (11/19) - Iowa Hawkeyes Football vs. Nebraska (11/25) - Iowa Hawkeyes Basketball vs. North Carolina (11/11) - Iowa Hawkeyes Basketball vs. Georgia Tech (11/29) Let me know if you'd have some time to chat in the coming weeks and we'd be thrilled to speak with you! Thanks, Josh Marcus CEO - Playbook Sports
A49: Freemium Tickets (team/state evergreen) | B49: DC Area Freemium Tickets Email (BDA Suite Blast) | C49: Sports Tix for the Holidays from Playbook Sports | D49: Josh Marcus | E49: jmarcus@callplaybook.com | F49: 2026-03-04 | G49: BDA Suite Blast | H49: HubSpot marketing email (live API page) | I49: 208716075623 | J49: No | K49: No | L49: https://www.callplaybook.com/get-started | https://www.callplaybook.com/washington-dc-ticket-registration | M49: Hi, My name is Josh Marcus and I am the CEO and Founder of Playbook Sports [https://www.callplaybook.com/get-started]. We’re an all-in-one sports management software solution designed to help sports business owners lean on technology to save admin time, and generate additional sign-ups and revenues for your programs. I just reached out via text and wanted to follow up with a unique offer since you’re an awesome sports leader in your community. With the holidays coming up we want to give back to the sports community. I have tickets [https://www.callplaybook.com/washington-dc-ticket-registration]for DC's sports teams this season at home that I would like to donate to you for leading in sports and for taking the time to connect with us. Feel free to pick one of the form links below (they all go to same form): 1. Washington Capitals [https://www.callplaybook.com/washington-dc-ticket-registration] 2. Washington Wizards [https://www.callplaybook.com/washington-dc-ticket-registration] 3. Georgetown Hoyas [https://www.callplaybook.com/washington-dc-ticket-registration] We believe Playbook can help your organization grow, and will host a free 30-minute Software Demonstration to visually show you how we can build solutions to improve your day-to-day operations, then donate the tickets to you or some. We hope to connect soon and see you at a game! Sincerely, Josh
A50: Freemium Tickets (team/state evergreen) | B50: Dallas Freemium Ticket View 10/18 (BDA Suite Blast) | C50: Would you like to attend a Mavericks or Stars game on Playbook? | D50: Josh Marcus | E50: jmarcus@callplaybook.com | F50: 2026-03-04 | G50: BDA Suite Blast | H50: HubSpot marketing email (live API page) | I50: 208719608505 | J50: No | K50: No | L50: https://www.callplaybook.com/features | M50: Hi, This is Josh Marcus, Founder and CEO of Playbook Sports [https://www.callplaybook.com/features], reaching out again. We're a SAAS tool designed to automate the day to day processes for sports and multi-purpose organizations and help them save time spent doing repetitive administrative tasks. From the looks of the {{ company.name }} website, it seems like you guys are running a fantastic operation and I believe Playbook would be a great fit for you and your team. I was hoping to link with you over a quick Zoom call to learn more about your organization, and show you exactly how Playbook can be a fit to help save admin time and provide a more streamlined experience for your participants as well! I would love to throw in free tickets to one of the following Mavericks or Stars games as well: - Thunder vs. OKC Thunder (10/29) - Thunder vs. Brooklyn Nets (11/07) - Thunder vs. LA Clippers (11/15) - Stars vs. Washington Capitals (10/27) - Stars vs. San Jose Sharks (11/11) - Stars vs. New York Islanders (11/19) Let me know if you'd have some time to chat in the coming weeks and we'd be thrilled to speak with you! Thanks, Josh Marcus CEO - Playbook Sports
A51: Demo / meeting | B51: Arrowhead Sideline Space for Demo Email (Mindbody Leads) (BDA Suite Blast) | C51: Free Field Slots at Arrowhead Stadium, Playbook Sports Events Special | D51: Josh Marcus | E51: jmarcus@callplaybook.com | F51: 2026-03-04 | H51: HubSpot marketing email (live API page) | I51: 208720045845 | J51: No | K51: No | L51: http://www.callplaybook.com/features | M51: Hello, I hope you are well. I am reaching out from Playbook Sports [http://www.callplaybook.com/features] because we have some field space available on the Arrowhead Stadium sideline and I think your program would be a great fit. I saw your organization while looking through local programs and think you would be able to run an awesome class, clinic, or training session with that hour of free field time. You can take advantage of the space for photos for your organization's social media and invite fans and family to come to watch. Are you interested in booking that field time at Arrowhead Stadium and a free software demo with Playbook? Sincerely, Josh I think we would be a great fit for you as a software partner too. Our software is built to streamline registration, member management, scheduling/staffing, financial reporting, and much more so that operating a community activities business is as easy as possible. For all organizations doing a stadium event with us, we provide a free demo of our software in a 20 or so minute, free, online meeting where we can compare what we offer to Mindbody.
A52: Freemium Tickets (team/state evergreen) | B52: Seattle Soccer Freemium Ticket View 8/22 (Clone) (BDA Suite Blast) | C52: Would you like to attend a Seattle Sounders Game on Playbook? | D52: Josh Marcus | E52: jmarcus@callplaybook.com | F52: 2026-03-04 | H52: HubSpot marketing email (live API page) | I52: 208720045842 | J52: No | K52: No | L52: https://www.callplaybook.com/features | M52: Hi, I'm Josh Marcus, Founder and CEO of Playbook Sports [https://www.callplaybook.com/features]. We're a SAAS tool designed to automate the day to day processes for sports and multi-purpose organizations and help them save time spent doing repetitive administrative tasks. I came across the {{ company.name }} website and it seems like you guys are running a fantastic operation; I believe Playbook would be a great fit for you and your team. I was hoping to link with you over a quick Zoom call to learn more about your organization, and show you exactly how Playbook can be a fit to help save admin time and provide a more streamlined experience for your participants as well! I would love to throw in free Sounders FC tickets to one of the following games as well: Houston Dynamo (9/4), FC Cincinnati (9/27), San Jose Earthquakes (10/9). Let me know if you'd have some time to chat in the coming weeks and we'd be thrilled to speak with you! Thanks, Josh Marcus CEO - Playbook Sports
A53: Freemium Tickets (team/state evergreen) | B53: Buffalo Freemium Ticket View 7/7 (BDA Suite Blast) | C53: Would you like to attend a Pro Sports Game??? | D53: Josh Marcus | E53: jmarcus@callplaybook.com | F53: 2026-03-04 | G53: BDA Suite Blast | H53: HubSpot marketing email (live API page) | I53: 208719811211 | J53: No | K53: No | L53: https://www.callplaybook.com/features | M53: Hi, I am Josh Marcus, Founder / CEO of Playbook Sports [https://www.callplaybook.com/features], a SAAS tool designed to automate all day to day processes for sports organizations. I came across the {{ company.name }} website and had to commend you for your contribution to your community. I was hoping I could link with you over a quick Zoom call, learn more about your organization and your future endeavors. I can also show you how Playbook Software has been working with other organizations to help them save admin time, and generate additional signups for your programs! I would love to throw in free tickets to an MLS game or the Buffalo Bisons. Let me know if you have a time that works conveniently for you in the coming weeks and we'd be thrilled to speak with you. Have a good and I look forward to chatting with you further. Thanks, Josh Marcus CEO - Playbook Sports
A54: Freemium Tickets (team/state evergreen) | B54: Pennsylvania All Teams Freemium Tickets Email (BDA Suite Blast) | C54: Your Pennsylvania Pro Sports Tickets from Playbook Sports | D54: Josh Marcus | E54: jmarcus@callplaybook.com | F54: 2026-03-04 | G54: BDA Suite Blast | H54: HubSpot marketing email (live API page) | I54: 208716324481 | J54: No | K54: No | L54: https://www.callplaybook.com/get-started | https://www.callplaybook.com/pennsylvania-ticket-registration | M54: Hi, My name is Josh Marcus and I am the CEO and Founder of Playbook Sports [https://www.callplaybook.com/get-started], an all-in-one sports management software solution designed for ease of use and simplifying processes. To the start the year off with some energy, we're donating basketball tickets to leaders in Pennsylvania. I just reached out via text but wanted to follow up here and say I have Sixers, Flyers, Penguins, Pitt Men's Basketball, and Penn State tickets for games this season at home that I would like to donate to you for being an awesome leader in sports (I also have tickets to the Phillies, Pirates, and Philadelphia Union if you'd prefer the spring/summer sports teams). Feel free to pick one of the form links [https://www.callplaybook.com/pennsylvania-ticket-registration] below or just reply to this email with which team you would like to claim tickets for, Playbook will follow up and confirm your reservation. 1. Philadelphia 76ers [https://www.callplaybook.com/pennsylvania-ticket-registration] 2. Philadelphia Flyers [https://www.callplaybook.com/pennsylvania-ticket-registration] 3. Pittsburgh Penguins [https://www.callplaybook.com/pennsylvania-ticket-registration] 4. Pitt Panthers/Penn State Nittany Lions [https://www.callplaybook.com/pennsylvania-ticket-registration] 5. Phillies/Union/Pirates Ticket Request [https://www.callplaybook.com/pennsylvania-ticket-registration] We hope to connect soon and see you at a game! Sincerely, Josh We are offering these tickets in tandem with a free software demo over Zoom where you will learn a bit about how we help organizations like yours beyond donating awesome sports tickets.
A55: Freemium Tickets (team/state evergreen) | B55: Memphis Freemium Ticket View 10/18 (BDA Suite Blast) | C55: Would you like to attend a Grizzlies game on Playbook? | D55: Josh Marcus | E55: jmarcus@callplaybook.com | F55: 2026-03-04 | G55: BDA Suite Blast | H55: HubSpot marketing email (live API page) | I55: 208719837586 | J55: No | K55: No | L55: https://www.callplaybook.com/features | M55: Hi, I'm Josh Marcus, Founder and CEO of Playbook Sports [https://www.callplaybook.com/features]. We're a SAAS tool designed to automate the day to day processes for sports and multi-purpose organizations and help them save time spent doing repetitive administrative tasks. I came across the {{ company.name }} website and it seems like you guys are running a fantastic operation; I believe Playbook would be a great fit for you and your team. I was hoping to link with you over a quick Zoom call to learn more about your organization, and show you exactly how Playbook can be a fit to help save admin time and provide a more streamlined experience for your participants as well! I would love to throw in free tickets to one of the following Grizzlies games as well: - Grizzlies vs. Brooklyn Nets (10/24) - Grizzlies vs. Celtics (11/07) - Grizzlies vs. Minnesota Timberwolves (11/11) Let me know if you'd have some time to chat in the coming weeks and we'd be thrilled to speak with you! Thanks, Josh Marcus CEO - Playbook Sports
A56: Freemium Tickets (team/state evergreen) | B56: Nevada All Teams Freemium Tickets Email (BDA Suite Blast) | C56: Your Nevada Sports Tickets from Playbook Sports | D56: Josh Marcus | E56: jmarcus@callplaybook.com | F56: 2026-03-04 | G56: BDA Suite Blast | H56: HubSpot marketing email (live API page) | I56: 208719193939 | J56: No | K56: No | L56: https://www.callplaybook.com/get-started | https://www.callplaybook.com/indiana-ticket-registration | M56: Hi, My name is Josh Marcus and I am the CEO and Founder of Playbook Sports [https://www.callplaybook.com/get-started], an all-in-one sports management software solution designed for ease of use and simplifying processes. We're donating sports tickets to leaders in Nevada. I just reached out via text but wanted to follow up here and say I have Reno Aces Minor League Baseball and Topgolf gift cards tickets for games/locations this season at home that I would like to donate to you for being an awesome leader in sports. Feel free to pick one of the form links [https://www.callplaybook.com/indiana-ticket-registration] below or just reply to this email with which team you would like to claim tickets for. Playbook will follow up and confirm your reservation. 1. Reno Aces [https://www.callplaybook.com/indiana-ticket-registration] 2. Topgolf [https://www.callplaybook.com/indiana-ticket-registration] We hope to connect soon and see you at a game! Sincerely, Josh We are offering these tickets in tandem with a free software demo over Zoom where you will learn a bit about how we help organizations like yours beyond donating awesome sports tickets.
A57: Template (master) | B57: Carolina 6/8 Ticket Template (Clone) (BDA Suite Blast) | C57: Would you like to see a Panthers or MiLB game on Playbook? | D57: Josh Marcus | E57: jmarcus@callplaybook.com | F57: 2026-03-04 | H57: HubSpot marketing email (live API page) | I57: 208715345564 | J57: No | K57: No | L57: https://www.callplaybook.com/features | M57: Hi there! I'm Josh, and I'm the Founder and CEO of Playbook Sports [https://www.callplaybook.com/features]. We provide tools designed to automate the day-to-day processes of sports organizations, and help business owners save time normally spent completing administrative tasks. I came across your website, and it seems like you all are running a fantastic operation! I believe Playbook would be a great fit for you and your team. I was hoping to connect on a quick call to learn more about your organization, and help see how Playbook can help save admin time, and help you spend more time with your athletes. With the summer season kicking into full gear, I would love to throw in free tickets to the following Panthers, Knights and RiverDogs games as well: - Carolina Panthers vs NY Jets (08/12) - Carolina Panthers vs Detroit Lions (08/25) - Charlotte Knights vs Louisville Bats (06/24) - Charlotte Knights vs Jacksonville Jumbo Shrimp (07/07) - Charleston RiverDogs vs Fayetteville Woodpeckers (06/24) - Charleston RiverDogs vs Columbia Fireflies (07/09) Let me know if you'd have some time to chat in the next week or two, and we'd be thrilled to speak with you! Thanks, Josh Marcus CEO - Playbook Sports
A58: Freemium Tickets (team/state evergreen) | B58: Minnesota Freemium View 11/4 (BDA Suite Blast) | C58: Would you like to see a Wild or Timberwolves game on Playbook? | D58: Josh Marcus | E58: jmarcus@callplaybook.com | F58: 2026-03-04 | G58: BDA Suite Blast | H58: HubSpot marketing email (live API page) | I58: 208716324478 | J58: No | K58: No | L58: https://www.callplaybook.com/features | M58: Hi, I'm Josh Marcus, Founder and CEO of Playbook Sports [https://www.callplaybook.com/features]. We're a SAAS tool designed to automate the day to day processes for sports and multi-purpose organizations and help them save time spent doing repetitive administrative tasks. I came across the {{ company.name }} website and it seems like you guys are running a fantastic operation; I believe Playbook would be a great fit for you and your team. I was hoping to link with you over a quick Zoom call to learn more about your organization, and show you exactly how Playbook can be a fit to help save admin time and provide a more streamlined experience for your participants! I would love to throw in free tickets to the following Wild or Timberwolves games as well: - Wild vs. San Jose Sharks (11/13) - Wild vs. Arizona Coyotes (11/27) - Wild vs. Edmonton Oilers (12/12) - Timberwolves vs. Miami Heat (11/21) - Timberwolves vs. Memphis Grizzlies (11/30) - Timberwolves vs. Dallas Mavericks (12/21) Let me know if you'd have some time to chat in the coming weeks and we'd be thrilled to speak with you! Thanks, Josh Marcus CEO - Playbook Sports
A59: Freemium Tickets (team/state evergreen) | B59: Portland Freemium Ticket View 12/17 (BDA Suite Blast) | C59: Would you like to see a Trail Blazers game on Playbook? | D59: Josh Marcus | E59: jmarcus@callplaybook.com | F59: 2026-03-04 | H59: HubSpot marketing email (live API page) | I59: 208715664434 | J59: No | K59: No | L59: https://www.callplaybook.com/features | M59: Hi, I'm Josh Marcus, Founder and CEO of Playbook Sports [https://www.callplaybook.com/features]. We're a SAAS tool designed to automate the day to day processes for sports and multi-purpose organizations and help them save time spent doing repetitive administrative tasks. I came across the {{ company.name }} website and it seems like you guys are running a fantastic operation; I believe Playbook would be a great fit for you and your team. I was hoping to link with you over a quick Zoom call to learn more about your organization, and show you exactly how Playbook can be a fit to help save admin time and provide a more streamlined experience for your participants! I would love to throw in two free tickets to the following Trail Blazers games as well: - Trail Blazers vs. Detroit Pistons (01/02) - Trail Blazers vs. Orlando Magic (01/10) - Trail Blazers vs. Dallas Mavericks (01/15) Let me know if you'd have some time to chat in the coming weeks and we'd be thrilled to speak with you! Thanks, Josh Marcus CEO - Playbook Sports
A60: Game Ticketblast | B60: LA Ticket Marketing Email June 3 (BDA Suite Blast) | C60: Would you like to attend a Pro Sports Game??? | D60: Josh Marcus | E60: jmarcus@callplaybook.com | F60: 2026-03-04 | G60: BDA Suite Blast | H60: HubSpot marketing email (live API page) | I60: 208716094053 | J60: No | K60: No | L60: https://www.callplaybook.com/features | M60: Hi, I am Josh Marcus, Founder / CEO of Playbook Sports [https://www.callplaybook.com/features], a SAAS tool designed to automate all day to day processes for sports organization. I came across the {{ company.name }} website and had to commend you for your contribution to your community. I was hoping I could link with you over a quick zoom call, learn more about your organization and show you our software. We'd love to show you how Playbook Software can help you save admin time, and generate additional signups for your programs! I am happy to throw in free tickets to an Angels, Dodgers or Padres game for you to attend as well. Let me know if you have a time that works conveniently for you in the coming week and I will be thrilled to speak with you. Have a super weekend and I look forward to chatting with you further. Thanks, Josh Marcus Playbook Sports
A61: Freemium Tickets (team/state evergreen) | B61: Non-City Freemium Ticket Gift Card Email (BDA Suite Blast) | C61: Sports Ticket/Gift Card Donation from Playbook Sports | D61: Josh Marcus | E61: jmarcus@callplaybook.com | F61: 2026-03-04 | H61: HubSpot marketing email (live API page) | I61: 208720045839 | J61: No | K61: No | L61: https://www.callplaybook.com/get-started | M61: Hi, My name is Josh Marcus and I am the CEO and Founder of Playbook Sports [https://www.callplaybook.com/get-started]. We’re an all-in-one sports management software solution designed to help sports business owners lean on technology to save admin time and generate additional sign-ups and revenues for your programs. Happy New Year! I just reached out via text and wanted to follow up with a unique offer since you’re an awesome sports leader in your community. To kick off 2022 on high note, I am hoping to connect with you and offer something special. With that being said, I have either a ticketmaster gift card or 2 tickets to the local sports event of your choice for this season that I would like to donate to you for leading in sports and for taking the time to meet with our team and join our network. We believe Playbook can help your organization grow, and will host a free 30-minute Software Demonstration to visually show you how we can build solutions to improve your day-to-day operations, then donate the tickets or gift card to you or someone in your organization. We hope to connect soon and see you at a game! Sincerely, Josh
A62: Freemium Tickets (team/state evergreen) | B62: Houston Rockets Freemium Tickets Email (BDA Suite Blast) | C62: Rockets Basketball from Playbook Sports | D62: Josh Marcus | E62: jmarcus@callplaybook.com | F62: 2026-03-04 | G62: BDA Suite Blast | H62: HubSpot marketing email (live API page) | I62: 208719837583 | J62: No | K62: No | L62: https://www.callplaybook.com/get-started | https://www.callplaybook.com/houstonrockets-ticket-registration | M62: Hi, My name is Josh Marcus and I am the CEO and Founder of Playbook Sports [https://www.callplaybook.com/get-started]. We’re an all-in-one sports management software solution designed to help sports business owners lean on technology to save admin time and generate additional sign-ups and revenues for your programs. Happy New Year! I just reached out via text and wanted to follow up with a unique offer since you’re an awesome sports leader in your community. To kick off 2022 on a high note, I wanted to reach out to connect with and give something back to local sports and activities leaders. With that being said, I have tickets for the Houston Rockets [https://www.callplaybook.com/houstonrockets-ticket-registration] this season at home that I would like to donate to you for leading in sports and for taking the time to meet with our team and join our network. Feel free to pick one of the form links below: 1.Rockets v. Toronto Raptors - 2/10/22 [https://www.callplaybook.com/houstonrockets-ticket-registration] 2.Rockets v. LA Clippers - 2/27 [https://www.callplaybook.com/houstonrockets-ticket-registration] 3.Rockets v. Sacramento Kings - 4/1/22 [https://www.callplaybook.com/houstonrockets-ticket-registration] 4. Houston Astros Ticket Request [https://www.callplaybook.com/houstonrockets-ticket-registration] [https://www.callplaybook.com/houstonrockets-ticket-registration] We believe Playbook can help your organization grow, and will host a free 30-minute Software Demonstration to visually show you how we can build solutions to improve your day-to-day operations, then donate the tickets to you or someone in your organization. We hope to connect soon and see you at a game! Sincerely, Josh
A63: Freemium Tickets (team/state evergreen) | B63: Colorado All Teams Freemium Tickets Email (BDA Suite Blast) | C63: Your Colorado Pro Sports Tickets from Playbook Sports | D63: Josh Marcus | E63: jmarcus@callplaybook.com | F63: 2026-03-04 | G63: BDA Suite Blast | H63: HubSpot marketing email (live API page) | I63: 208716324475 | J63: No | K63: No | L63: https://www.callplaybook.com/colorado-ticket-registration | https://www.callplaybook.com/get-started | M63: Hi, My name is Josh Marcus and I am the CEO and Founder of Playbook Sports [https://www.callplaybook.com/get-started], an all-in-one sports management software solution designed for ease of use and simplifying processes. To the start off with some energy, we're donating sports tickets to leaders in Colorado. I just reached out via text but wanted to follow up here and say I have Denver Nuggets, Colorado Avalanche, Rockies (when MLB lockout ends), Colorado Rapids tickets for games this season at home that I would like to donate to you for being an awesome leader in sports. Feel free to pick one of the form links [https://www.callplaybook.com/colorado-ticket-registration] below or just reply to this email with which team you would like to claim tickets for. Playbook will follow up and confirm your reservation. 1. Denver Nuggets [https://www.callplaybook.com/colorado-ticket-registration] 2. Colorado Avalanche [https://www.callplaybook.com/colorado-ticket-registration] 3. Colorado Rockies [https://www.callplaybook.com/colorado-ticket-registration] 4. Colorado Rapids [https://www.callplaybook.com/colorado-ticket-registration] We hope to connect soon and see you at a game! Sincerely, Josh We are offering these tickets in tandem with a free software demo over Zoom where you will learn a bit about how we help organizations like yours beyond donating awesome sports tickets.
A64: Freemium Tickets (team/state evergreen) | B64: Portland Freemium Tickets Email (BDA Suite Blast) | C64: Portland Pro Sports Tickets from Playbook Sports | D64: Josh Marcus | E64: jmarcus@callplaybook.com | F64: 2026-03-04 | H64: HubSpot marketing email (live API page) | I64: 208719193936 | J64: No | K64: No | L64: https://www.callplaybook.com/get-started | https://www.callplaybook.com/portland-ticket-registration | M64: Hi, My name is Josh Marcus and I am the CEO and Founder of Playbook Sports [https://www.callplaybook.com/get-started], an all-in-one sports management software solution designed for ease of use and simplifying processes. To the start the year off with some energy, we're donating sports tickets to leaders in Portland. I just reached out via text but wanted to follow up here and say I have Portland Trail Blazers, Portland Timbers, and Oregon State Beavers Men's Basketball tickets for games this season, at home, that I would like to donate to you for being an awesome leader in sports and for doing a brief software demo with us. Feel free to pick one of the form links [https://www.callplaybook.com/portland-ticket-registration] below or just reply to this email with which team you would like to claim tickets for. Playbook will follow up and confirm your reservation. 1. Portland Trail Blazers [https://www.callplaybook.com/portland-ticket-registration] 2. Portland Timbers [https://www.callplaybook.com/portland-ticket-registration] 3. Oregon State Beavers Men's Basketball [https://www.callplaybook.com/portland-ticket-registration] We hope to connect soon and see you at a game! Sincerely, Josh We are offering these tickets in tandem with a free software demo over Zoom where you will learn a bit about how we help organizations like yours beyond just donating awesome sports tickets.
A65: Freemium Tickets (team/state evergreen) | B65: Maryland Freemium View 10/24 (BDA Suite Blast) | C65: Would you like to attend a Commanders Game on Playbook? | D65: Josh Marcus | E65: jmarcus@callplaybook.com | F65: 2026-03-04 | G65: BDA Suite Blast | H65: HubSpot marketing email (live API page) | I65: 208719811202 | J65: No | K65: No | L65: https://www.callplaybook.com/features | M65: Hi, I'm Josh Marcus, Founder and CEO of Playbook Sports [https://www.callplaybook.com/features]. We're a SAAS tool designed to automate the day to day processes for sports and multi-purpose organizations and help them save time spent doing repetitive administrative tasks. I came across the {{ company.name }} website and it seems like you guys are running a fantastic operation; I believe Playbook would be a great fit for you and your team. I was hoping to link with you over a quick Zoom call to learn more about your organization, and show you exactly how Playbook can be a fit to help save admin time and provide a more streamlined experience for your participants! I would love to throw in free tickets to the following Commanders games as well: - Commanders vs. Atlanta Falcons (11/27) - Commanders vs. NY Giants (12/18) - Commanders vs. Cleveland Browns (01/01/23) Let me know if you'd have some time to chat in the coming weeks and we'd be thrilled to speak with you! Thanks, Josh Marcus CEO - Playbook Sports
A66: Freemium Tickets (team/state evergreen) | B66: Georgia Freemium Ticket View 05/11 (BDA Suite Blast) | C66: Would you like to see a Braves game on Playbook? | D66: Josh Marcus | E66: jmarcus@callplaybook.com | F66: 2026-03-04 | G66: BDA Suite Blast | H66: HubSpot marketing email (live API page) | I66: 208716094050 | J66: No | K66: No | L66: https://www.callplaybook.com/features | M66: Hi, I'm Josh Marcus, Founder and CEO of Playbook Sports [https://www.callplaybook.com/features]. We're a SAAS tool designed to automate the day to day processes for sports and multi-purpose organizations and help them save time spent doing repetitive administrative tasks. I came across the {{ company.name }} website and it seems like you guys are running a fantastic operation; I believe Playbook would be a great fit for you and your team. I was hoping to link with you over a quick Zoom call to learn more about your organization, and show you exactly how Playbook can be a fit to help save admin time and provide a more streamlined experience for your participants! I would love to throw in free tickets to the following Braves games as well: - Braves vs. Seattle Mariners (05/20) - Braves vs. LA Dodgers (05/22) - Braves vs. Philadelphia Phillies (05/26) Let me know if you'd have some time to chat in the coming weeks and we'd be thrilled to speak with you! Thanks, Josh Marcus CEO - Playbook Sports
A67: Game Ticketblast | B67: Illinois Ticket Marketing Email May 10 (BDA Suite Blast) | C67: Would you like to attend a Pro Sports Game??? | D67: Josh Marcus | E67: jmarcus@callplaybook.com | F67: 2026-03-04 | H67: HubSpot marketing email (live API page) | I67: 208720175885 | J67: No | K67: No | L67: https://www.callplaybook.com/features | M67: Hi, I am Josh Marcus, Founder / CEO of Playbook Sports [https://www.callplaybook.com/features], a SAAS tool designed to automate all day to day processes for sports organization. I came across the {{ company.name }} website and had to commend you for your contribution to your community. I was hoping I could link with you over a quick zoom call, learn more about your organization and show you our software. We'd love to get your feedback on our product and gain some perspective from you. I am happy to throw in free tickets to a Cubs, White Sox or an MLS game for you to attend as well. Let me know if you have a time that works conveniently for you in the coming week and I will be thrilled to speak with you. Have a super weekend and I look forward to chatting with you further. Thanks, Josh Marcus Playbook Sports
A68: Template (master) | B68: Carolina 6/8 Ticket Template (BDA Suite Blast) | C68: Would you like to see a Panthers or MiLB game on Playbook? | D68: Josh Marcus | E68: jmarcus@callplaybook.com | F68: 2026-03-04 | H68: HubSpot marketing email (live API page) | I68: 208715664431 | J68: No | K68: No | L68: https://www.callplaybook.com/features | M68: Hi there! I'm Josh, and I'm the Founder and CEO of Playbook Sports [https://www.callplaybook.com/features]. We provide tools designed to automate the day-to-day processes of sports organizations, and help business owners save time normally spent completing administrative tasks. I came across your website, and it seems like you all are running a fantastic operation! I believe Playbook would be a great fit for you and your team. I was hoping to connect on a quick call to learn more about your organization, and help see how Playbook can help save admin time, and help you spend more time with your athletes. With the summer season kicking into full gear, I would love to throw in free tickets to the following Panthers, Knights and RiverDogs games as well: - Carolina Panthers vs NY Jets (08/12) - Carolina Panthers vs Detroit Lions (08/25) - Charlotte Knights vs Louisville Bats (06/24) - Charlotte Knights vs Jacksonville Jumbo Shrimp (07/07) - Charleston RiverDogs vs Fayetteville Woodpeckers (06/24) - Charleston RiverDogs vs Columbia Fireflies (07/09) Let me know if you'd have some time to chat in the next week or two, and we'd be thrilled to speak with you! Thanks, Josh Marcus CEO - Playbook Sports
A69: Freemium Tickets (team/state evergreen) | B69: Mass Freemium Hockey (BDA Suite Blast) | C69: Would you like to attend a Pro Sports Game??? | D69: Josh Marcus | E69: jmarcus@callplaybook.com | F69: 2026-03-04 | G69: BDA Suite Blast | H69: HubSpot marketing email (live API page) | I69: 208720327046 | J69: No | K69: No | L69: https://www.callplaybook.com/features | M69: Hi, I'm Josh Marcus, Founder and CEO of Playbook Sports [https://www.callplaybook.com/features]. We're a SAAS tool designed to automate the day to day processes for sports and multi-purpose organizations and help them save time spent doing repetitive administrative tasks. I came across the {{ company.name }} website and it seems like you guys are running a fantastic operation; I believe Playbook would be a great fit for you and your team. I was hoping to link with you over a quick Zoom call to learn more about your organization, and show you exactly how Playbook can be a fit to help save admin time and provide a more streamlined exeprience for your participants as well! I would love to throw in free tickets to the Bruins against the Panthers (10/17), Stars (10/25), or Flames (10/10) as well. Let me know if you'd have some time to chat in the coming weeks and we'd be thrilled to speak with you! Thanks, Josh Marcus CEO - Playbook Sports
A70: Freemium Tickets (team/state evergreen) | B70: Virginia Freemium View 10/24 (Clone) (BDA Suite Blast) | C70: Would you like to attend a Cavaliers Football or Basketball Game on Playbook? | D70: Josh Marcus | E70: jmarcus@callplaybook.com | F70: 2026-03-04 | G70: BDA Suite Blast | H70: HubSpot marketing email (live API page) | I70: 208719608502 | J70: No | K70: No | L70: https://www.callplaybook.com/features | M70: Hi, I'm Josh Marcus, Founder and CEO of Playbook Sports [https://www.callplaybook.com/features]. We're a SAAS tool designed to automate the day to day processes for sports and multi-purpose organizations and help them save time spent doing repetitive administrative tasks. I came across the {{ company.name }} website and it seems like you guys are running a fantastic operation; I believe Playbook would be a great fit for you and your team. I was hoping to link with you over a quick Zoom call to learn more about your organization, and show you exactly how Playbook can be a fit to help save admin time and provide a more streamlined experience for your participants! I would love to throw in free tickets to the following Virginia Cavaliers football and basketball games as well: - Cavaliers Football vs. UNC Tar Heels (11/05) - Cavaliers Football vs. Pittsburgh Panthers (11/12) - Cavaliers Basketball vs. Florida State Seminoles (12/03) - Cavaliers Basketball vs. University of Houston Cougars (12/17) Let me know if you'd have some time to chat in the coming weeks and we'd be thrilled to speak with you! Thanks, Josh Marcus CEO - Playbook Sports
A71: Freemium Tickets (team/state evergreen) | B71: Edmonton Freemium Ticket View 8/12 (BDA Suite Blast) | C71: Would you like to attend a Pro Sports Game??? | D71: Josh Marcus | E71: jmarcus@callplaybook.com | F71: 2026-03-04 | G71: BDA Suite Blast | H71: HubSpot marketing email (live API page) | I71: 208719193933 | J71: No | K71: No | L71: https://www.callplaybook.com/features | M71: Hi, I'm Josh Marcus, Founder and CEO of Playbook Sports [https://www.callplaybook.com/features]. We're a SAAS tool designed to automate the day to day processes for sports and multi-purpose organizations and help them save time spent doing repetitive administrative tasks. I came across the {{ company.name }} website and it seems like you guys are running a fantastic operation; I believe Playbook would be a great fit for you and your team. I was hoping to link with you over a quick Zoom call to learn more about your organization, and show you exactly how Playbook can be a fit to help save admin time and provide a more streamlined exeprience for your participants as well! I would love to throw in free tickets to see the Edmonton Oilers play the Sabres (10/18), Kings (11/16) or Panthers (11/28) as well. Let me know if you'd have some time to chat in the coming weeks and we'd be thrilled to speak with you! Thanks, Josh Marcus CEO - Playbook Sports
A72: Freemium Tickets (team/state evergreen) | B72: Toronto Hockey Freemium View 9/1 (BDA Suite Blast) | C72: Would you like to attend a Maple Leafs Game on Playbook? | D72: Josh Marcus | E72: jmarcus@callplaybook.com | F72: 2026-03-04 | G72: BDA Suite Blast | H72: HubSpot marketing email (live API page) | I72: 208718954892 | J72: No | K72: No | L72: https://www.callplaybook.com/features | M72: Hi, I'm Josh Marcus, Founder and CEO of Playbook Sports [https://www.callplaybook.com/features]. We're a SAAS tool designed to automate the day to day processes for sports and multi-purpose organizations and help them save time spent doing repetitive administrative tasks. I came across the {{ company.name }} website and it seems like you guys are running a fantastic operation; I believe Playbook would be a great fit for you and your team. I was hoping to link with you over a quick Zoom call to learn more about your organization, and show you exactly how Playbook can be a fit to help save admin time and provide a more streamlined experience for your participants! I would love to throw in free tickets to the following Maple Leafs games as well: - Maple Leafs vs Senators (9/24) - Maple Leafs vs Canadiens (9/28) - Maple Leafs vs Red Wings (10/8) Let me know if you'd have some time to chat in the coming weeks and we'd be thrilled to speak with you! Thanks, Josh Marcus CEO - Playbook Sports
A73: Freemium Tickets (team/state evergreen) | B73: Calgary Freemium Ticket View 11/23 (BDA Suite Blast) | C73: Would you like to see a Flames game on Playbook? | D73: Josh Marcus | E73: jmarcus@callplaybook.com | F73: 2026-03-04 | H73: HubSpot marketing email (live API page) | I73: 208720045836 | J73: No | K73: No | L73: https://www.callplaybook.com/features | M73: Hi, I'm Josh Marcus, Founder and CEO of Playbook Sports [https://www.callplaybook.com/features]. We're a SAAS tool designed to automate the day to day processes for sports and multi-purpose organizations and help them save time spent doing repetitive administrative tasks. I came across the {{ company.name }} website and it seems like you guys are running a fantastic operation; I believe Playbook would be a great fit for you and your team. I was hoping to link with you over a quick Zoom call to learn more about your organization, and show you exactly how Playbook can be a fit to help save admin time and provide a more streamlined experience for your participants! I would love to throw in two free tickets to the following Flames games as well: - Flames vs. Arizona Coyotes (12/05) - Flames vs. Minnesota Wild (12/07) - Flames vs. Vancouver Canucks (12/14) Let me know if you'd have some time to chat in the coming weeks and we'd be thrilled to speak with you! Thanks, Josh Marcus CEO - Playbook Sports
A74: Freemium Tickets (team/state evergreen) | B74: Georgia Soccer Freemium Ticket View 8/25 (BDA Suite Blast) | C74: Would you like to attend an Atlanta United FC Game on Playbook? | D74: Josh Marcus | E74: jmarcus@callplaybook.com | F74: 2026-03-04 | G74: BDA Suite Blast | H74: HubSpot marketing email (live API page) | I74: 208716075620 | J74: No | K74: No | L74: https://www.callplaybook.com/features | M74: Hi, I'm Josh Marcus, Founder and CEO of Playbook Sports [https://www.callplaybook.com/features]. We're a SAAS tool designed to automate the day to day processes for sports and multi-purpose organizations and help them save time spent doing repetitive administrative tasks. I came across the {{ company.name }} website and it seems like you guys are running a fantastic operation; I believe Playbook would be a great fit for you and your team. I was hoping to link with you over a quick Zoom call to learn more about your organization, and show you exactly how Playbook can be a fit to help save admin time and provide a more streamlined exeprience for your participants as well! I would love to throw in free tickets to the Atlanta United FC against the Toronto FC (9/10), Philadelphia Union (9/17), or NYCFC (10/9) as well. Let me know if you'd have some time to chat in the coming weeks and we'd be thrilled to speak with you! Thanks, Josh Marcus CEO - Playbook Sports
A75: Freemium Tickets (team/state evergreen) | B75: Texas All Teams Freemium Tickets Email (BDA Suite Blast) | C75: Your NBA Tickets from Playbook Sports | D75: Josh Marcus | E75: jmarcus@callplaybook.com | F75: 2026-03-04 | G75: BDA Suite Blast | H75: HubSpot marketing email (live API page) | I75: 208719837576 | J75: No | K75: No | L75: https://www.callplaybook.com/dallas-mavs-ticket-registration | https://www.callplaybook.com/get-started | https://www.callplaybook.com/houstonrockets-ticket-registration | https://www.callplaybook.com/san-antonio-spurs-ticket-registration | M75: Hi, My name is Josh Marcus and I am the CEO and Founder of Playbook Sports [https://www.callplaybook.com/get-started], an all-in-one sports management software solution designed for ease of use and simplifying processes. I'm reaching out because I'm donating pro sports tickets to activity and athletic program leaders in Texas. I have Rockets, Spurs, and Mavericks as well as Astros and Rangers tickets for games this season at home that I would like to donate to you for being an awesome leader in sports. Feel free to pick one of the form links below or just reply to this email with which team you would like to claim tickets for, Playbook will follow up and confirm your reservation. 1. Houston Rockets/Astros [https://www.callplaybook.com/houstonrockets-ticket-registration] 2. San Antonio Spurs [https://www.callplaybook.com/san-antonio-spurs-ticket-registration] 3. Dallas Mavs/Texas Rangers [https://www.callplaybook.com/dallas-mavs-ticket-registration] We hope to connect soon and see you at a game! Sincerely, Josh We are offering these tickets in tandem with a free software demo over Zoom where you will learn a bit about how we help organizations like yours beyond donating awesome sports tickets.
A76: Template (master) | B76: Cleveland 6/7 Ticket Template (BDA Suite Blast) | C76: Would you like to see a Guardians game on Playbook? | D76: Josh Marcus | E76: jmarcus@callplaybook.com | F76: 2026-03-04 | G76: BDA Suite Blast | H76: HubSpot marketing email (live API page) | I76: 208716094044 | J76: No | K76: No | L76: https://www.callplaybook.com/features | M76: Hi there! I'm Josh, and I'm the Founder and CEO of Playbook Sports [https://www.callplaybook.com/features]. We provide tools designed to automate the day-to-day processes of sports organizations, and help business owners save time normally spent completing administrative tasks. I came across your website, and it seems like you all are running a fantastic operation! I believe Playbook would be a great fit for you and your team. I was hoping to connect on a quick call to learn more about your organization, and help see how Playbook can help save admin time, and help you spend more time with your athletes. To celebrate the baseball season swinging into gear, I would love to throw in free tickets to the following Guardians games as well: - Cleveland Guardians vs Oakland Athletics (06/20) - Cleveland Guardians vs Milwaukee Brewers (06/23) - Cleveland Guardians vs Atlanta Braves (07/03) Let me know if you'd have some time to chat in the next week or two, and we'd be thrilled to speak with you! Thanks, Josh Marcus CEO - Playbook Sports
A77: Freemium Tickets (team/state evergreen) | B77: Winnipeg Freemium Tickets Email (BDA Suite Blast) | C77: Winnipeg Jets Tickets from Playbook Sports | D77: Josh Marcus | E77: jmarcus@callplaybook.com | F77: 2026-03-04 | G77: BDA Suite Blast | H77: HubSpot marketing email (live API page) | I77: 208718954889 | J77: No | K77: No | L77: https://www.callplaybook.com/get-started | https://www.callplaybook.com/winnipeg-ticket-registration | M77: Hi, My name is Josh Marcus and I am the CEO and Founder of Playbook Sports [https://www.callplaybook.com/get-started], an all-in-one sports management software solution designed for ease of use and simplifying processes. To the start off with some energy, we're donating sports tickets to leaders in and around Winnipeg. I just reached out via text but wanted to follow up here and say I have Winnipeg Jets tickets for a few home games this season that I would like to donate to you for being an awesome leader in sports and for doing a brief software demo with us. Feel free to pick one of the form links [https://www.callplaybook.com/winnipeg-ticket-registration] below or just reply to this email with which team you would like to claim tickets for. Playbook will follow up and confirm your reservation. 1. Jets v. Stars - 3/4/22 [https://www.callplaybook.com/winnipeg-ticket-registration] 2. Jets v. Coyotes - 3/27/22 [https://www.callplaybook.com/winnipeg-ticket-registration] 3. Jets v. Red Wings - 4/6/22 [https://www.callplaybook.com/winnipeg-ticket-registration] We hope to connect soon and see you at a game! Sincerely, Josh We are offering these tickets in tandem with a free software demo over Zoom where you will learn a bit about how we help organizations like yours beyond just donating awesome sports tickets. Once you attend one of our demo meetings, you will know exactly how we can add value for you and your organization and I will then get you the tickets.
A78: Freemium Tickets (team/state evergreen) | B78: Memphis Grizzlies Freemium Tickets Email (BDA Suite Blast) | C78: Memphis Grizzlies Tickets on us, from Playbook Sports | D78: Josh Marcus | E78: josh.marcus@callplaybook.com | F78: 2026-03-04 | G78: BDA Suite Blast | H78: HubSpot marketing email (live API page) | I78: 208716324469 | J78: No | K78: No | L78: https://www.callplaybook.com/get-started | https://www.callplaybook.com/memphis-grizzlies-ticket-registration | M78: Hi, My name is Josh Marcus and I am the CEO and Founder of Playbook Sports [https://www.callplaybook.com/get-started], an all-in-one sports management software solution designed for ease of use and simplifying processes. I just reached out via text but wanted to follow up here and say I have some extra Memphis Grizzlies tickets for games this season at the FedEx Forum that I would like to personally invite you to in exchange for doing a quick software demo with us over Zoom. Feel free to pick one [https://www.callplaybook.com/memphis-grizzlies-ticket-registration] of the games below or just reply to this email with which game you would like to claim tickets for, Playbook will follow up and confirm your reservation. Grizzlies v. Suns - Friday 11/12/21 [https://www.callplaybook.com/memphis-grizzlies-ticket-registration] Grizzlies v. Trail Blazers - Sunday 12/19/21 [https://www.callplaybook.com/memphis-grizzlies-ticket-registration] Grizzlies v. Wizards - Saturday 1/29/22 [https://www.callplaybook.com/memphis-grizzlies-ticket-registration] We hope to connect soon and see you at a game! Sincerely, Josh We are offering these tickets in tandem with a free software demo over Zoom where you will learn a bit about how we help organizations like yours beyond offering Grizzlies tickets.
A79: Freemium Tickets (team/state evergreen) | B79: Bay Area Freemium Tickets Email (BDA Suite Blast) | C79: Warriors or Sharks tix - Happy New Year from Playbook Sports | D79: Josh Marcus | E79: jmarcus@callplaybook.com | F79: 2026-03-04 | G79: BDA Suite Blast | H79: HubSpot marketing email (live API page) | I79: 208719608499 | J79: No | K79: No | L79: https://www.callplaybook.com/get-started | https://www.callplaybook.com/san-jose-ticket-registration | M79: Hi, Happy New Year. My name is Josh Marcus and I am the CEO and Founder of Playbook Sports [https://www.callplaybook.com/get-started]. We’re an all-in-one sports management software solution designed to help sports business owners lean on technology and give their websites tools built with ease of use as a priority the drive sign-ups and save time. We want show you our product and give back to kick off the new year on an exciting note. I just reached out via text and wanted to follow up with a unique offer since you’re an awesome sports leader in your community. I have tickets for the Golden State Warriors (first-come first-serve) or San Jose Sharks [https://www.callplaybook.com/san-jose-ticket-registration] this season at home that I would like to donate to you for leading in sports and for taking the time to meet with our team and join our network. We believe Playbook can help your organization grow, and will host a free 30-minute Software Demonstration to visually show you how we can build solutions to improve your day-to-day operations, then donate the tickets to you or someone in your organization. We hope to connect soon and see you at a game! Sincerely, Josh
A80: Game Ticketblast | B80: Pennsylvania Ticket Marketing Email May 3 (BDA Suite Blast) | C80: Would you like to attend a Pro Sports Game??? | D80: Josh Marcus | E80: jmarcus@callplaybook.com | F80: 2026-03-04 | G80: BDA Suite Blast | H80: HubSpot marketing email (live API page) | I80: 208716094041 | J80: No | K80: No | L80: https://www.callplaybook.com/features | M80: Hi, I am Josh Marcus, Founder / CEO of Playbook Sports [https://www.callplaybook.com/features], a SAAS tool designed to automate all day to day processes for sports organization. I came across the {{ company.name }} website and had to commend you for your contribution to your community. I was hoping I could link with you over a quick zoom call, learn more about your organization and show you our software. We'd love to get your feedback on our product and gain some perspective from you. I am happy to throw in free tickets to a Pirates, Phillies or an MLS game for you to attend as well. Let me know if you have a time that works conveniently for you in the coming week and I will be thrilled to speak with you. Have a super weekend and I look forward to chatting with you further. Thanks, Josh Marcus Playbook Sports
A81: Freemium Tickets (team/state evergreen) | B81: Illinois Freemium Ticket View 8/8 (BDA Suite Blast) | C81: Would you like to attend a Pro Sports Game??? | D81: Josh Marcus | E81: jmarcus@callplaybook.com | F81: 2026-03-04 | G81: BDA Suite Blast | H81: HubSpot marketing email (live API page) | I81: 208720045833 | J81: No | K81: No | L81: https://www.callplaybook.com/features | M81: Hi, I'm Josh Marcus, Founder and CEO of Playbook Sports [https://www.callplaybook.com/features]. We're a SAAS tool designed to automate the day to day processes for sports organizations to make their lives easier and give them more time to focus on the important things. I came across the {{ company.name }} website and it seems like you guys are running a fantastic operation, and I believe Playbook could be a great fit for you and your team. I was hoping to link with you over a quick Zoom call to learn more about your organization and future endeavors. I can also show you exactly how Playbook Software can be a fit to help save admin time and generate additional signups for your programs! I would love to throw in free tickets to the Cubs, White Sox or Chicago Fire as well. Let me know if you'd have some time to chat in the coming weeks and we'd be thrilled to speak with you! Have a good day and I look forward to chatting with you further. Thanks, Josh Marcus CEO - Playbook Sports
A82: Freemium Tickets (team/state evergreen) | B82: Indiana All Teams Freemium Tickets Email (BDA Suite Blast) | C82: Your Indiana Pro/NCAA Sports Tickets from Playbook Sports | D82: Josh Marcus | E82: jmarcus@callplaybook.com | F82: 2026-03-04 | G82: BDA Suite Blast | H82: HubSpot marketing email (live API page) | I82: 208719811199 | J82: No | K82: No | L82: https://www.callplaybook.com/get-started | https://www.callplaybook.com/indiana-ticket-registration | M82: Hi, My name is Josh Marcus and I am the CEO and Founder of Playbook Sports [https://www.callplaybook.com/get-started], an all-in-one sports management software solution designed for ease of use and simplifying processes. To the start the year off with some energy, we're donating sports tickets to leaders in Indiana. I just reached out via text but wanted to follow up here and say I have Indiana Pacers, Notre Dame Fighting Irish Men's Basketball, and Indiana Hoosiers Men's Basketball tickets for games this season at home that I would like to donate to you for being an awesome leader in sports. Feel free to pick one of the form links [https://www.callplaybook.com/indiana-ticket-registration] below or just reply to this email with which team you would like to claim tickets for. Playbook will follow up and confirm your reservation. 1. Indiana Pacers [https://www.callplaybook.com/indiana-ticket-registration] 2. Notre Dame Fighting Irish [https://www.callplaybook.com/indiana-ticket-registration] 3. Indiana Hoosiers [https://www.callplaybook.com/indiana-ticket-registration] We hope to connect soon and see you at a game! Sincerely, Josh We are offering these tickets in tandem with a free software demo over Zoom where you will learn a bit about how we help organizations like yours beyond donating awesome sports tickets.
A83: Freemium Tickets (team/state evergreen) | B83: Boston Celtics Freemium Tickets Email (BDA Suite Blast) | C83: Celtics/Red Sox Game from Playbook Sports | D83: Josh Marcus | E83: jmarcus@callplaybook.com | F83: 2026-03-04 | G83: BDA Suite Blast | H83: HubSpot marketing email (live API page) | I83: 208719837573 | J83: No | K83: No | L83: https://www.callplaybook.com/atlanta-hawks-ticket-registration | https://www.callplaybook.com/boston-celtics-ticket-registration | https://www.callplaybook.com/get-started | M83: Hi, My name is Josh Marcus and I am the CEO and Founder of Playbook Sports [https://www.callplaybook.com/get-started], an all-in-one sports management software solution designed for ease of use and simplifying processes. Happy New Year! To the start the year off with some energy, we're donating basketball tickets to leaders in Massachusetts. I just reached out via text but wanted to follow up here and say I have some Boston Celtics [https://www.callplaybook.com/boston-celtics-ticket-registration] [https://www.callplaybook.com/atlanta-hawks-ticket-registration] for games this season at home that I would like to donate to you for being an awesome leader in sports (I also have Red Sox tickets for the upcoming season if you would prefer Fenway to TD Garden). Feel free to pick one of the form links below or just reply to this email with which team you would like to claim tickets for, Playbook will follow up and confirm your reservation. 1. Celtics v. Indiana Pacers - 1/10/22 [https://www.callplaybook.com/boston-celtics-ticket-registration] 2. Celtics v. Sacramento Kings - 1/25/22 [https://www.callplaybook.com/boston-celtics-ticket-registration] 3. Celtics v. Memphis Grizzlies - 3/3/22 [https://www.callplaybook.com/boston-celtics-ticket-registration] 4. Red Sox Ticket Request [https://www.callplaybook.com/boston-celtics-ticket-registration] We hope to connect soon and see you at a game! Sincerely, Josh We are offering these tickets in tandem with a free software demo over Zoom where you will learn a bit about how we help organizations like yours beyond donating awesome sports tickets.
A84: Freemium Tickets (team/state evergreen) | B84: Mass Hockey Freemium View 9/27 (BDA Suite Blast) | C84: Would you like to attend a Bruins Game on Playbook? | D84: Josh Marcus | E84: jmarcus@callplaybook.com | F84: 2026-03-04 | H84: HubSpot marketing email (live API page) | I84: 208718954886 | J84: No | K84: No | L84: https://www.callplaybook.com/features | M84: Hi, I'm Josh Marcus, Founder and CEO of Playbook Sports [https://www.callplaybook.com/features]. We're a SAAS tool designed to automate the day to day processes for sports and multi-purpose organizations and help them save time spent doing repetitive administrative tasks. I came across the {{ company.name }} website and it seems like you guys are running a fantastic operation; I believe Playbook would be a great fit for you and your team. I was hoping to link with you over a quick Zoom call to learn more about your organization, and show you exactly how Playbook can be a fit to help save admin time and provide a more streamlined experience for your participants! I would love to throw in free tickets to the following Miami Heat, Gators or Seminoles games as well: - Bruins vs. Florida Panthers (10/17) - Bruins vs. Dallas Stars (10/25) - Bruins vs. New York Islanders (12/13) Let me know if you'd have some time to chat in the coming weeks and we'd be thrilled to speak with you! Thanks, Josh Marcus CEO - Playbook Sports
A85: Freemium Tickets (team/state evergreen) | B85: Indiana Freemium Ticket View 12/1 (BDA Suite Blast) | C85: Would you like to see a Pacers game on Playbook? | D85: Josh Marcus | E85: jmarcus@callplaybook.com | F85: 2026-03-04 | G85: BDA Suite Blast | H85: HubSpot marketing email (live API page) | I85: 208716094038 | J85: No | K85: No | L85: https://www.callplaybook.com/features | M85: Hi, I'm Josh Marcus, Founder and CEO of Playbook Sports [https://www.callplaybook.com/features]. We're a SAAS tool designed to automate the day to day processes for sports and multi-purpose organizations and help them save time spent doing repetitive administrative tasks. I came across the {{ company.name }} website and it seems like you guys are running a fantastic operation; I believe Playbook would be a great fit for you and your team. I was hoping to link with you over a quick Zoom call to learn more about your organization, and show you exactly how Playbook can be a fit to help save admin time and provide a more streamlined experience for your participants! I would love to throw in two free tickets to the following Pacers games as well: - Pacers vs. NY Knicks (12/18) - Pacers vs. Atlanta Hawks (12/27) - Pacers vs. LA Clippers (12/31) Let me know if you'd have some time to chat in the coming weeks and we'd be thrilled to speak with you! Thanks, Josh Marcus CEO - Playbook Sports
A86: Freemium Tickets (team/state evergreen) | B86: Los Angeles Freemium 9/6 (BDA Suite Blast) (Variation) | C86: Would you like to attend a Lakers/Chargers Game on Playbook? | D86: Josh Marcus | E86: jmarcus@callplaybook.com | F86: 2026-03-04 | G86: BDA Suite Blast | H86: HubSpot marketing email (live API page) | I86: 208715415952 | J86: No | K86: No | L86: https://www.callplaybook.com/features | M86: I'm Josh Marcus, Founder and CEO of Playbook Sports [https://www.callplaybook.com/features]. We're a SAAS tool designed to automate the day to day processes for sports and multi-purpose organizations and help them save time spent doing repetitive administrative tasks. I came across the {{ company.name }} website and it seems like you guys are running a fantastic operation; I believe Playbook would be a great fit for you and your team. I was hoping to link with you over a quick Zoom call to learn more about your organization, and show you exactly how Playbook can be a fit to help save admin time and provide a more streamlined experience for your participants! I would love to throw in free tickets to one of the following Lakers or Chargers games: - Chargers vs. Jaguars (9/25/22) - Chargers vs. Titans (12/18/22) - Lakers vs. Pacers (11/28/22) - Lakers vs. Kings (1/18/23) Let me know if you'd have some time to chat in the coming weeks and we'd be thrilled to speak with you! Thanks, Josh Marcus CEO - Playbook Sports
A87: Freemium Tickets (team/state evergreen) | B87: Los Angeles Freemium 9/6 (BDA Suite Blast) | C87: Would you like to attend a Lakers/Chargers Game on Playbook? | D87: Josh Marcus | E87: jmarcus@callplaybook.com | F87: 2026-03-04 | G87: BDA Suite Blast | H87: HubSpot marketing email (live API page) | I87: 208715415948 | J87: No | K87: No | L87: https://www.callplaybook.com/features | M87: I'm Josh Marcus, Founder and CEO of Playbook Sports [https://www.callplaybook.com/features]. We're a SAAS tool designed to automate the day to day processes for sports and multi-purpose organizations and help them save time spent doing repetitive administrative tasks. I came across the {{ company.name }} website and it seems like you guys are running a fantastic operation; I believe Playbook would be a great fit for you and your team. I was hoping to link with you over a quick Zoom call to learn more about your organization, and show you exactly how Playbook can be a fit to help save admin time and provide a more streamlined experience for your participants as well! I would love to throw in free tickets to one of the following Lakers or Chargers games: - Chargers vs. Jaguars (9/25/22) - Chargers vs. Titans (12/18/22) - Lakers vs. Pacers (11/28/22) - Lakers vs. Kings (1/18/23) Let me know if you'd have some time to chat in the coming weeks and we'd be thrilled to speak with you! Thanks, Josh Marcus CEO - Playbook Sports
A88: Freemium Tickets (team/state evergreen) | B88: Cleveland Freemium Tickets Email (BDA Suite Blast) | C88: Cleveland Pro Sports Tickets from Playbook Sports | D88: Josh Marcus | E88: jmarcus@callplaybook.com | F88: 2026-03-04 | G88: BDA Suite Blast | H88: HubSpot marketing email (live API page) | I88: 208719608493 | J88: No | K88: No | L88: https://www.callplaybook.com/cleveland-ticket-registration | https://www.callplaybook.com/get-started | M88: Hi, My name is Josh Marcus and I am the CEO and Founder of Playbook Sports [https://www.callplaybook.com/get-started], an all-in-one sports management software solution designed for ease of use and simplifying processes. To the start the year off with some energy, we're donating sports tickets to leaders in Cleveland. I just reached out via text but wanted to follow up here and say I have Cleveland Cavaliers and Cleveland Guardians tickets for games this season, at home, that I would like to donate to you for being an awesome leader in sports and for doing a brief software demo with us. Feel free to pick one of the form links [https://www.callplaybook.com/cleveland-ticket-registration] below or just reply to this email with which team you would like to claim tickets for. Playbook will follow up and confirm your reservation. 1. Cleveland Cavaliers [https://www.callplaybook.com/cleveland-ticket-registration] 2. Cleveland Guardians [https://www.callplaybook.com/cleveland-ticket-registration] We hope to connect soon and see you at a game! Sincerely, Josh We are offering these tickets in tandem with a free software demo over Zoom where you will learn a bit about how we help organizations like yours beyond just donating awesome sports tickets. Once you attend one of our demo meetings, you will know exactly how we can add value for you and your organization and I will then get you the tickets.
A89: Game Ticketblast | B89: Kentucky Ticket Marketing Email June 15 (BDA Suite Blast) | C89: Would you like to attend a Pro Sports Game??? | D89: Josh Marcus | E89: jmarcus@callplaybook.com | F89: 2026-03-04 | G89: BDA Suite Blast | H89: HubSpot marketing email (live API page) | I89: 208715345558 | J89: No | K89: No | L89: https://www.callplaybook.com/features | M89: Hi, I am Josh Marcus, Founder / CEO of Playbook Sports [https://www.callplaybook.com/features], a SAAS tool designed to automate all day to day processes for sports organizations. I came across the {{ company.name }} website and had to commend you for your contribution to your community. I was hoping I could link with you over a quick zoom call, learn more about your organization and show you our software. I would love to show you how Playbook Software can help you save admin time, and generate additional signups for your programs! I am happy to throw in free tickets to a Bowling Green Hot Rods, Louisville Bats, Louisville City FC or Racing Louisville game for you to attend as well. Let me know if you have a time that works conveniently for you in the coming week and I will be thrilled to speak with you. Have a super weekend and I look forward to chatting with you further. Thanks, Josh Marcus Playbook Sports
A90: Game Ticketblast | B90: Connecticut Ticket Marketing Email June 9 (BDA Suite Blast) | C90: Would you like to attend a Pro Sports Game??? | D90: Josh Marcus | E90: jmarcus@callplaybook.com | F90: 2026-03-04 | H90: HubSpot marketing email (live API page) | I90: 208720045830 | J90: No | K90: No | L90: https://www.callplaybook.com/features | M90: Hi, I am Josh Marcus, Founder / CEO of Playbook Sports [https://www.callplaybook.com/features], a SAAS tool designed to automate all day to day processes for sports organizations. I came across the {{ company.name }} website and had to commend you for your contribution to your community. I was hoping I could link with you over a quick zoom call, learn more about your organization and show you our software. I would love to show you how Playbook Software can help you save admin time, and generate additional signups for your programs! I am happy to throw in free tickets to a Red Sox, Yankees, Mets, Revolution or NYCFC game for you to attend as well. Let me know if you have a time that works conveniently for you in the coming week and I will be thrilled to speak with you. Have a super weekend and I look forward to chatting with you further. Thanks, Josh Marcus Playbook Sports
A91: Freemium Tickets (team/state evergreen) | B91: San Antonio Spurs Freemium Tickets Email New Year (BDA Suite Blast) | C91: Spurs Basketball for the New Year from Playbook Sports | D91: Josh Marcus | E91: jmarcus@callplaybook.com | F91: 2026-03-04 | G91: BDA Suite Blast | H91: HubSpot marketing email (live API page) | I91: 208719811192 | J91: No | K91: No | L91: https://www.callplaybook.com/get-started | https://www.callplaybook.com/san-antonio-spurs-ticket-registration | M91: Hi, My name is Josh Marcus and I am the CEO and Founder of Playbook Sports [https://www.callplaybook.com/get-started]. We’re an all-in-one sports management software solution designed to help sports business owners lean on technology to save admin time and generate additional sign-ups and revenues for your programs. Happy New Year! I just reached out via text and wanted to follow up with a unique offer since you’re an awesome sports leader in your community. To kick off 2022 on high note, I am hoping to connect with you and offer something special. With that being said, I have tickets for the San Antonio Spurs [https://www.callplaybook.com/san-antonio-spurs-ticket-registration] this season at home that I would like to donate to you for leading in sports and for taking the time to meet with our team and join our network. Feel free to pick one of the form links below: 1 .Spurs v. Nets - Friday 1/21/22 [https://www.callplaybook.com/san-antonio-spurs-ticket-registration] 2. Spurs v. Jazz - Friday 3/11/22 [https://www.callplaybook.com/san-antonio-spurs-ticket-registration] 3. Spurs v. Pelicans - Friday 3/18/22 [https://www.callplaybook.com/san-antonio-spurs-ticket-registration] We believe Playbook can help your organization grow, and will host a free 30-minute Software Demonstration to visually show you how we can build solutions to improve your day-to-day operations, then donate the tickets to you or someone in your organization. We hope to connect soon and see you at a game! Sincerely, Josh
A92: Freemium Tickets (team/state evergreen) | B92: Salt Lake City Freemium View 9/1 (BDA Suite Blast) | C92: Would you like to attend a Jazz Game on Playbook? | D92: Josh Marcus | E92: jmarcus@callplaybook.com | F92: 2026-03-04 | G92: BDA Suite Blast | H92: HubSpot marketing email (live API page) | I92: 208719193927 | J92: No | K92: No | L92: https://www.callplaybook.com/features | M92: Hi, I'm Josh Marcus, Founder and CEO of Playbook Sports [https://www.callplaybook.com/features]. We're a SAAS tool designed to automate the day to day processes for sports and multi-purpose organizations and help them save time spent doing repetitive administrative tasks. I came across the {{ company.name }} website and it seems like you guys are running a fantastic operation; I believe Playbook would be a great fit for you and your team. I was hoping to link with you over a quick Zoom call to learn more about your organization, and show you exactly how Playbook can be a fit to help save admin time and provide a more streamlined experience for your participants! I would love to throw in free tickets to the following Utah Jazz games as well: - Utah Jazz vs Dener Nuggets (10/19) - Utah Jazz vs Memphis Grizzlies (10/29) - Utah Jazz vs Phoenix Knights (11/18) Let me know if you'd have some time to chat in the coming weeks and we'd be thrilled to speak with you! Thanks, Josh Marcus CEO - Playbook Sports
A93: Freemium Tickets (team/state evergreen) | B93: Phoenix Freemium View 10/11 (BDA Suite Blast) | C93: Would you like to attend a Cardinals Game on Playbook? | D93: Josh Marcus | E93: jmarcus@callplaybook.com | F93: 2026-03-04 | H93: HubSpot marketing email (live API page) | I93: 208720175799 | J93: No | K93: No | L93: https://www.callplaybook.com/features | M93: Hi, I'm Josh Marcus, Founder and CEO of Playbook Sports [https://www.callplaybook.com/features]. We're a SAAS tool designed to automate the day to day processes for sports and multi-purpose organizations and help them save time spent doing repetitive administrative tasks. I came across the {{ company.name }} website and it seems like you guys are running a fantastic operation; I believe Playbook would be a great fit for you and your team. I was hoping to link with you over a quick Zoom call to learn more about your organization, and show you exactly how Playbook can be a fit to help save admin time and provide a more streamlined experience for your participants! I would love to throw in free tickets to the following Cardinals games as well: - Cardinals vs. New Orleans Saints (10/20) - Cardinals vs. Seattle Seahawks (11/06) - Cardinals vs. LA Chargers (11/27) Let me know if you'd have some time to chat in the coming weeks and we'd be thrilled to speak with you! Thanks, Josh Marcus CEO - Playbook Sports
A94: Freemium Tickets (team/state evergreen) | B94: Memphis Grizzlies New Years Freemium Tickets Email (BDA Suite Blast) | C94: Memphis Grizzlies Ticket Donation Info from Playbook | D94: Josh Marcus | E94: jmarcus@callplaybook.com | F94: 2026-03-04 | G94: BDA Suite Blast | H94: HubSpot marketing email (live API page) | I94: 208716324466 | J94: No | K94: No | L94: https://www.callplaybook.com/get-started | https://www.callplaybook.com/memphisgrizzlies-ticket-registration | M94: Hi, My name is Josh Marcus and I am the CEO and Founder of Playbook Sports [https://www.callplaybook.com/get-started], an all-in-one sports management software solution designed for ease of use and simplifying processes. Happy New Year! We are in the spirit of connecting and giving to kick off 2022 on a high note here at Playbook. With that being said, I just reached out via text but wanted to follow up here and say I have some extra Memphis Grizzlies tickets for games this season at home at the FedExForum that I would like to donate to you for being an awesome leader for sports in your community. Feel free to pick one [https://www.callplaybook.com/memphisgrizzlies-ticket-registration] of the games below or just reply to this email with which game you would like to claim tickets for, Playbook will follow up and confirm your reservation. Grizzlies v. Washington Wizards - 1/29/22 [https://www.callplaybook.com/memphisgrizzlies-ticket-registration] Grizzlies v. Portland Trail Blazers - 2/16/22 [https://www.callplaybook.com/memphisgrizzlies-ticket-registration] Grizzlies v. New York Knicks - 3/11/22 [https://www.callplaybook.com/memphisgrizzlies-ticket-registration] We hope to connect soon and see you at a game! Sincerely, Josh We are offering these tickets in tandem with a free software demo over Zoom where you will learn a bit about how we help organizations like yours beyond donating Grizzlies tickets. We can integrate registration tools, schedulers, staff management, communication and marketing features, and much more. We'll show you how we will customize your experience with our software to best suit your organization.
A95: Freemium Tickets (team/state evergreen) | B95: Oklahoma Freemium Ticket View 8/19 (BDA Suite Blast) | C95: Would you like to attend a Sooners/Thunder Game on Playbook? | D95: Josh Marcus | E95: jmarcus@callplaybook.com | F95: 2026-03-04 | H95: HubSpot marketing email (live API page) | I95: 208719837570 | J95: No | K95: No | L95: https://www.callplaybook.com/features | M95: Hi, I'm Josh Marcus, Founder and CEO of Playbook Sports [https://www.callplaybook.com/features]. We're a SAAS tool designed to automate the day to day processes for sports and multi-purpose organizations and help them save time spent doing repetitive administrative tasks. I came across the {{ company.name }} website and it seems like you guys are running a fantastic operation; I believe Playbook would be a great fit for you and your team. I was hoping to link with you over a quick Zoom call to learn more about your organization, and show you exactly how Playbook can be a fit to help save admin time and provide a more streamlined exeprience for your participants as well! I would love to throw in free tickets to one of the following games as well: Sooners v. Miners (9/3), Sooners v. Kent State (9/10), Thunder v. Timberwolves (10/23), Thunder v. Sixers (12/31). Let me know if you'd have some time to chat in the coming weeks and we'd be thrilled to speak with you! Thanks, Josh Marcus CEO - Playbook Sports
A96: Freemium Tickets (team/state evergreen) | B96: Philadelphia Freemium Ticket View 10/18 (BDA Suite Blast) | C96: Would you like to attend a 76ers or Flyers game on Playbook? | D96: Josh Marcus | E96: jmarcus@callplaybook.com | F96: 2026-03-04 | H96: HubSpot marketing email (live API page) | I96: 208718954877 | J96: No | K96: No | L96: https://www.callplaybook.com/features | M96: Hi, This is Josh Marcus, Founder and CEO of Playbook Sports [https://www.callplaybook.com/features], reaching out again. We're a SAAS tool designed to automate the day to day processes for sports and multi-purpose organizations and help them save time spent doing repetitive administrative tasks. From the looks of the {{ company.name }} website, it seems like you guys are running a fantastic operation and I believe Playbook would be a great fit for you and your team. I was hoping to link with you over a quick Zoom call to learn more about your organization, and show you exactly how Playbook can be a fit to help save admin time and provide a more streamlined experience for your participants as well! I would love to throw in free tickets to one of the following 76ers or Flyers games as well: - 76ers vs. Phoenix Suns (11/07) - 76ers vs. Minnesota Timberwolves (11/19) - 76ers vs. Atlanta Hawks (11/28) - Flyers vs. Carolina Hurricanes (10/29) - Flyers vs. St Louis Blues (11/08) - Flyers vs. Dallas Stars (11/13) Let me know if you'd have some time to chat in the coming weeks and we'd be thrilled to speak with you! Thanks, Josh Marcus CEO - Playbook Sports
A97: Freemium Tickets (team/state evergreen) | B97: Orlando Freemium View 11/2 (Clone) (BDA Suite Blast) | C97: Would you like to see a Magic/Lightning game on Playbook? | D97: Josh Marcus | E97: jmarcus@callplaybook.com | F97: 2026-03-04 | G97: BDA Suite Blast | H97: HubSpot marketing email (live API page) | I97: 208715415945 | J97: No | K97: No | L97: https://www.callplaybook.com/features | M97: Hi, I'm Josh Marcus, Founder and CEO of Playbook Sports [https://www.callplaybook.com/features]. We're a SAAS tool designed to automate the day to day processes for sports and multi-purpose organizations and help them save time spent doing repetitive administrative tasks. I came across the {{ company.name }} website and it seems like you guys are running a fantastic operation; I believe Playbook would be a great fit for you and your team. I was hoping to link with you over a quick Zoom call to learn more about your organization, and show you exactly how Playbook can be a fit to help save admin time and provide a more streamlined experience for your participants! I would love to throw in free tickets to the following Magic or Lightning games as well: - Magic vs. Phoenix Suns (11/11) - Magic vs. Philadelphia 76ers (11/27) - Magic vs. Milwaukee Bucks (12/05) - Lightning vs. Washington Capitals (11/13) - Lightning vs. Philadelphia 76ers (11/27) - Lightning vs. Milwaukee Bucks (12/05) Let me know if you'd have some time to chat in the coming weeks and we'd be thrilled to speak with you! Thanks, Josh Marcus CEO - Playbook Sports
A98: Freemium Tickets (team/state evergreen) | B98: Milwaukee Freemium Ticket View 8/25 (Clone) (BDA Suite Blast) | C98: Would you like to attend a Bucks or Brewers Game on Playbook? | D98: Josh Marcus | E98: jmarcus@callplaybook.com | F98: 2026-03-04 | G98: BDA Suite Blast | H98: HubSpot marketing email (live API page) | I98: 208716094035 | J98: No | K98: No | L98: https://www.callplaybook.com/features | M98: Hi, I'm Josh Marcus, Founder and CEO of Playbook Sports [https://www.callplaybook.com/features]. We're a SAAS tool designed to automate the day to day processes for sports and multi-purpose organizations and help them save time spent doing repetitive administrative tasks. I came across the {{ company.name }} website and it seems like you guys are running a fantastic operation; I believe Playbook would be a great fit for you and your team. I was hoping to link with you over a quick Zoom call to learn more about your organization, and show you exactly how Playbook can be a fit to help save admin time and provide a more streamlined exeprience for your participants as well! I would love to throw in free tickets to the following games as well: - Brewers vs Pirates (8/31) - Brewers vs Reds (9/10) - Bucks vs Pistons (11/2) - Bucks vs Trail Blazers (11/21) Let me know if you'd have some time to chat in the coming weeks and we'd be thrilled to speak with you! Thanks, Josh Marcus CEO - Playbook Sports
A99: Freemium Tickets (team/state evergreen) | B99: DC Freemium (BDA Suite Blast) | C99: Would you like to attend a Pro Sports Game??? | D99: Josh Marcus | E99: jmarcus@callplaybook.com | F99: 2026-03-04 | H99: HubSpot marketing email (live API page) | I99: 208720120077 | J99: No | K99: No | L99: https://www.callplaybook.com/features | M99: I'm Josh Marcus, Founder and CEO of Playbook Sports [https://www.callplaybook.com/features]. We're a SAAS tool designed to automate the day to day processes for sports and multi-purpose organizations and help them save time spent doing repetitive administrative tasks. I came across the {{ company.name }} website and it seems like you guys are running a fantastic operation; I believe Playbook would be a great fit for you and your team. I was hoping to link with you over a quick Zoom call to learn more about your organization, and show you exactly how Playbook can be a fit to help save admin time and provide a more streamlined exeprience for your participants as well! I would love to throw in free tickets to the Texans against the 49ers (8/25), Colts (9/11) or Chargers (10/2) as well. Let me know if you'd have some time to chat in the coming weeks and we'd be thrilled to speak with you! Thanks, Josh Marcus CEO - Playbook Sports
A100: Freemium Tickets (team/state evergreen) | B100: UConn Freemium Tickets Email (BDA Suite Blast) | C100: UConn Basketball for the Holidays from Playbook Sports | D100: Josh Marcus | E100: jmarcus@callplaybook.com | F100: 2026-03-04 | G100: BDA Suite Blast | H100: HubSpot marketing email (live API page) | I100: 208715664425 | J100: No | K100: No | L100: https://www.callplaybook.com/get-started | https://www.callplaybook.com/uconn-huskies-ticket-registration | M100: Hi, My name is Josh Marcus and I am the CEO and Founder of Playbook Sports [https://www.callplaybook.com/get-started]. We’re an all-in-one sports management software solution designed to help sports business owners lean on technology to save admin time and generate additional sign-ups and revenues for your programs. Our clients' websites have tools that are built with ease of use as a priority. We want show you our product and give back this holiday season in one fell swoop. I just reached out via text and wanted to follow up with a unique offer since you’re an awesome sports leader in your community. I have tickets for this season at home that I would like to donate to you for leading in sports and for taking the time to meet with our team and join our network. Feel free to pick one of the form links below: 1. Huskies v. Grambling - 12/4/21 [https://www.callplaybook.com/uconn-huskies-ticket-registration] 2. Huskies v. Creighton - 2/1/22 [https://www.callplaybook.com/uconn-huskies-ticket-registration] 3. Huskies v. DePaul - 3/5/22 [https://www.callplaybook.com/uconn-huskies-ticket-registration] We believe Playbook can help your organization grow, and will host a free 30-minute Software Demonstration to visually show you how we can build solutions to improve your day-to-day operations, then donate the tickets to you or someone in your organization. We hope to connect soon and see you at a game! Sincerely, Josh
A101: Freemium Tickets (team/state evergreen) | B101: New Mexico Freemium View 9/15 (BDA Suite Blast) | C101: Would you like to attend a New Mexico United/Lobos Game on Playbook? | D101: Josh Marcus | E101: jmarcus@callplaybook.com | F101: 2026-03-04 | G101: BDA Suite Blast | H101: HubSpot marketing email (live API page) | I101: 208716324463 | J101: No | K101: No | L101: https://www.callplaybook.com/features | M101: Hi, I'm Josh Marcus, Founder and CEO of Playbook Sports [https://www.callplaybook.com/features]. We're a SAAS tool designed to automate the day to day processes for sports and multi-purpose organizations and help them save time spent doing repetitive administrative tasks. I came across the {{ company.name }} website and it seems like you guys are running a fantastic operation; I believe Playbook would be a great fit for you and your team. I was hoping to link with you over a quick Zoom call to learn more about your organization, and show you exactly how Playbook can be a fit to help save admin time and provide a more streamlined experience for your participants! I would love to throw in free tickets to the following New Mexico United/Lobos Football games as well: - Colorado Spring Switchbacks FC @ New Mexico United (10/15) - LA Galaxy II @ New Mexico United (10/31) - New Mexico Lobos @ New Mexico State Aggies (10/15) - San Diego Aztecs @ New Mexico Lobos (11/18) Let me know if you'd have some time to chat in the coming weeks and we'd be thrilled to speak with you! Thanks, Josh Marcus CEO - Playbook Sports
A102: Freemium Tickets (team/state evergreen) | B102: Washington Freemium 9/12 (BDA Suite Blast) | C102: Would you like to attend a Mariners/Kraken Game on Playbook? | D102: Josh Marcus | E102: jmarcus@callplaybook.com | F102: 2026-03-04 | G102: BDA Suite Blast | H102: HubSpot marketing email (live API page) | I102: 208715415942 | J102: No | K102: No | L102: https://www.callplaybook.com/features | M102: I'm Josh Marcus, Founder and CEO of Playbook Sports [https://www.callplaybook.com/features]. We're a SAAS tool designed to automate the day to day processes for sports and multi-purpose organizations and help them save time spent doing repetitive administrative tasks. I came across the {{ company.name }} website and it seems like you guys are running a fantastic operation; I believe Playbook would be a great fit for you and your team. I was hoping to link with you over a quick Zoom call to learn more about your organization, and show you exactly how Playbook can be a fit to help save admin time and provide a more streamlined experience for your participants! I would love to throw in free tickets to one of the following Mariners/Kraken games: - Seattle Mariners vs Texas Rangers (9/28) - Seattle Mariners vs Oakland Athletics (10/1) - Seattle Kraken vs. Edmonton Oilers (9/26) - Seattle Kraken vs. Calgary Flames (9/27) Let me know if you'd have some time to chat in the coming weeks and we'd be thrilled to speak with you! Thanks, Josh Marcus CEO - Playbook Sports
A103: Freemium Tickets (team/state evergreen) | B103: Alabama State Freemium View 11/9 (BDA Suite Blast) | C103: Would you like to see an Alabama basketball game on Playbook? | D103: Josh Marcus | E103: jmarcus@callplaybook.com | F103: 2026-03-04 | G103: BDA Suite Blast | H103: HubSpot marketing email (live API page) | I103: 208720120073 | J103: No | K103: No | L103: https://www.callplaybook.com/features | M103: Hi, I'm Josh Marcus, Founder and CEO of Playbook Sports [https://www.callplaybook.com/features]. We're a SAAS tool designed to automate the day to day processes for sports and multi-purpose organizations and help them save time spent doing repetitive administrative tasks. I came across the {{ company.name }} website and it seems like you guys are running a fantastic operation; I believe Playbook would be a great fit for you and your team. I was hoping to link with you over a quick Zoom call to learn more about your organization, and show you exactly how Playbook can be a fit to help save admin time and provide a more streamlined experience for your participants! I would love to throw in free tickets to the following Alabama basketball games as well: - Alabama vs. Memphis Tigers (12/13) - Alabama vs. Ole Miss Rebels (01/03) - Alabama vs. LSU Tigers (01/14) Let me know if you'd have some time to chat in the coming weeks and we'd be thrilled to speak with you! Thanks, Josh Marcus CEO - Playbook Sports
A104: Freemium Tickets (team/state evergreen) | B104: Minneapolis Baseball Freemium Ticket View 8/22 (BDA Suite Blast) | C104: Would you like to attend a Twins Game on Playbook? | D104: Josh Marcus | E104: jmarcus@callplaybook.com | F104: 2026-03-04 | G104: BDA Suite Blast | H104: HubSpot marketing email (live API page) | I104: 208715664422 | J104: No | K104: No | L104: https://www.callplaybook.com/features | M104: Hi, I'm Josh Marcus, Founder and CEO of Playbook Sports [https://www.callplaybook.com/features]. We're a SAAS tool designed to automate the day to day processes for sports and multi-purpose organizations and help them save time spent doing repetitive administrative tasks. I came across the {{ company.name }} website and it seems like you guys are running a fantastic operation; I believe Playbook would be a great fit for you and your team. I was hoping to link with you over a quick Zoom call to learn more about your organization, and show you exactly how Playbook can be a fit to help save admin time and provide a more streamlined experience for your participants as well! I would love to throw in free Twins tickets to one of the following games as well: Guardians (9/10), Royals (9/12), Angels (9/24). Let me know if you'd have some time to chat in the coming weeks and we'd be thrilled to speak with you! Thanks, Josh Marcus CEO - Playbook Sports
A105: Freemium Tickets (team/state evergreen) | B105: Dallas Basketball Freemium Ticket View 8/25 (Clone) (BDA Suite Blast) | C105: Would you like to attend a Dallas Mavericks Game on Playbook? | D105: Josh Marcus | E105: jmarcus@callplaybook.com | F105: 2026-03-04 | H105: HubSpot marketing email (live API page) | I105: 208715664419 | J105: No | K105: No | L105: https://www.callplaybook.com/features | M105: Hi, I'm Josh Marcus, Founder and CEO of Playbook Sports [https://www.callplaybook.com/features]. We're a SAAS tool designed to automate the day to day processes for sports and multi-purpose organizations and help them save time spent doing repetitive administrative tasks. I came across the {{ company.name }} website and it seems like you guys are running a fantastic operation; I believe Playbook would be a great fit for you and your team. I was hoping to link with you over a quick Zoom call to learn more about your organization, and show you exactly how Playbook can be a fit to help save admin time and provide a more streamlined experience for your participants as well! I would love to throw in free Dallas Mavericks tickets to the following games as well:Thunder (10/29), Raptors (11/4) or Nuggets (11/20). Let me know if you'd have some time to chat in the coming weeks and we'd be thrilled to speak with you! Thanks, Josh Marcus CEO - Playbook Sports
A106: Demo / meeting | B106: Metlife Sideline Space for Demo Email (BDA Suite Blast) | C106: Free Sideline Slots at Metlife Stadium (3/7-3/13), Playbook Sports Events Special Offer | D106: Josh Marcus | E106: jmarcus@callplaybook.com | F106: 2026-03-04 | G106: BDA Suite Blast | H106: HubSpot marketing email (live API page) | I106: 208719811189 | J106: No | K106: No | L106: http://www.callplaybook.com/features | M106: Hello, I hope you are well. I am reaching out from Playbook Sports [http://www.callplaybook.com/features] because we have some field space available on the Metlife Stadium sideline during the week of 3/7/22 and I think your program would be a great fit. We are a management software and events company and are looking to expand our local network from our home base in NJ. I saw your organization while looking through local programs and think you would be able to run an awesome class, clinic, or training session with that hour of free field time. You can take advantage of the space for photos for your organizations social media and invite fans and family to come watch. Are you interested in booking that field time at Metlife and a free software demo with Playbook? Sincerely, Josh I think we would be a great fit for you as a software partner too. Our software is built to streamline registration, member management, scheduling/staffing, financial reporting, and much more so that operating a community activities business is as easy as possible. For all organizations doing a stadium event with us, we provide a free demo of our software in a 20 or so minute, free, online meeting.
...
